Workbook

Sheet Employee_Master
A1: Fully Automatic Employee Master Dashboard Source Data
A2: Emp_ID | B2: Emp_Name | C2: Department | D2: Designation | E2: Joining Date | F2: CL Allocated | G2: SL Allocated | H2: EL Allocated | I2: Basic Salary | J2: Status | K2: Gender
A3: EMP001 | B3: Aman Khan | C3: Management | D3: Manager | E3: 45292 | F3: 12 | G3: 12 | H3: 10 | I3: 30000 | J3: Active | K3: Male
A4: EMP002 | B4: Neha Sharma | C4: Engineering | D4: Engineer | E4: 45337 | F4: 12 | G4: 12 | H4: 10 | I4: 25000 | J4: Active | K4: Female
A5: EMP003 | B5: Ali Raza | C5: Technical | D5: Supervisor | E5: 45361 | F5: 12 | G5: 12 | H5: 10 | I5: 18000 | J5: Active | K5: Male
A6: EMP004 | B6: Riya Singh | C6: Technical | D6: S. Tech | E6: 45402 | F6: 12 | G6: 12 | H6: 10 | I6: 15000 | J6: Active | K6: Female
A7: EMP005 | B7: Shah Alam | C7: Technical | D7: S. Tech | E7: 45423 | F7: 12 | G7: 12 | H7: 10 | I7: 15000 | J7: Active | K7: Male
A8: EMP006 | B8: Karan Gupta | C8: Technical | D8: S. Tech | E8: 45444 | F8: 12 | G8: 12 | H8: 10 | I8: 15000 | J8: Active | K8: Male
A9: EMP007 | B9: Irfan Pathan | C9: Technical | D9: Tech | E9: 45474 | F9: 12 | G9: 12 | H9: 10 | I9: 12000 | J9: Active | K9: Male
A10: EMP008 | B10: Pappi Singh | C10: Technical | D10: Tech | E10: 45491 | F10: 12 | G10: 12 | H10: 10 | I10: 12000 | J10: Active | K10: Male
A11: EMP009 | B11: Raju Roi | C11: Technical | D11: Tech | E11: 45506 | F11: 12 | G11: 12 | H11: 10 | I11: 12000 | J11: Active | K11: Male
A12: EMP010 | B12: Rabia Ansari | C12: Technical | D12: Tech | E12: 45519 | F12: 12 | G12: 12 | H12: 10 | I12: 12000 | J12: Active | K12: Female
A13: EMP011 | B13: Ram Kumar | C13: Support | D13: Helper | E13: 45536 | F13: 12 | G13: 12 | H13: 10 | I13: 10000 | J13: Active | K13: Male
A14: EMP012 | B14: Raja Babu | C14: Support | D14: Helper | E14: 45580 | F14: 12 | G14: 12 | H14: 10 | I14: 10000 | J14: Active | K14: Male
... A702: EMP0700 | B702: Asif Jain | C702: Technical | D702: Sr. Technician | E702: 46119 | F702: 12 | G702: 12 | H702: 10 | I702: 44137 | J702: Active | K702: Female

Sheet Payroll_Data
A1: Year | B1: Month | C1: Management | D1: Administrative Staff | E1: Sales Department | F1: Production Department | G1: Logistics Department | H1: Basic Payroll | I1: Bonuses and Prizes | J1: Payroll Taxes & Insurance | K1: Payroll | L1: Annual Payroll Plan | M1: Standard Hours | N1: Actual Hours | O1: Head Office | P1: Regional Offices | Q1: Regional Branches | R1: Remote Employees | S1: Outsourcing | T1: A | U1: B | V1: C | W1: D | X1: E | Y1: A | Z1: B | AA1: C | AB1: D | AC1: E | AD1: SU | AE1: MO | AF1: TU | AG1: WE | AH1: TH | AI1: FR | AJ1: SA | AK1: SU | AL1: MO | AM1: TU | AN1: WE | AO1: TH | AP1: FR | AQ1: SA | AR1: Employee1 | AS1: Employee2 | AT1: Employee3 | AU1: Employee4 | AV1: Employee5 | AW1: Employee1 | AX1: Employee2 | AY1: Employee3 | AZ1: Employee4 | BA1: Employee5
A2: 2025 | B2: JAN | C2: 28340 | D2: 18130 | E2: 20185 | F2: 20270 | G2: 20710 | H2: 0.4 | I2: 0.41 | J2: 0.19 | K2: 107635 | L2: 120000 | M2: 0.33 | N2: 0.71 | O2: 0.26 | P2: 0.23 | Q2: 0.12 | R2: 0.11 | S2: 0.28 | T2: 1.08 | U2: 0.47 | V2: 1.34 | W2: 0.47 | X2: 0.5 | Y2: 0.46 | Z2: 0.39 | AA2: 0.59 | AB2: 0.48 | AC2: 0.7 | AD2: 59867 | AE2: 29705 | AF2: 695 | AG2: 88522 | AH2: 10928 | AI2: 15996 | AJ2: 34287 | AK2: 33107 | AL2: 10047 | AM2: 37625 | AN2: 42413 | AO2: 37885 | AP2: 27649 | AQ2: 31454 | AR2: 5200 | AS2: 3100 | AT2: 6300 | AU2: 6000 | AV2: 6600 | AW2: 7300 | AX2: 4300 | AY2: 4500 | AZ2: 4100 | BA2: 4100
A3: 2025 | B3: FEB | C3: 33090 | D3: 19480 | E3: 23855 | F3: 43990 | G3: 33180 | H3: 0.37 | I3: 0.43 | J3: 0.2 | K3: 153595 | L3: 120000 | M3: 0.17 | N3: 0.5 | O3: 0.34 | P3: 0.23 | Q3: 0.12 | R3: 0.12 | S3: 0.19 | T3: 0.91 | U3: 0.54 | V3: 1.32 | W3: 0.52 | X3: 1.13 | Y3: 0.48 | Z3: 0.56 | AA3: 0.57 | AB3: 0.38 | AC3: 0.64 | AD3: 10456 | AE3: 27396 | AF3: 49816 | AG3: 34348 | AH3: 38205 | AI3: 45492 | AJ3: 34287 | AK3: 42731 | AL3: 41459 | AM3: 21075 | AN3: 31812 | AO3: 21932 | AP3: 38151 | AQ3: 32860 | AR3: 9300 | AS3: 2900 | AT3: 3800 | AU3: 4800 | AV3: 6100 | AW3: 3600 | AX3: 5700 | AY3: 5400 | AZ3: 3300 | BA3: 3700
A4: 2025 | B4: MAR | C4: 31685 | D4: 33955 | E4: 27270 | F4: 34630 | G4: 29220 | H4: 0.35 | I4: 0.48 | J4: 0.17 | K4: 156760 | L4: 120000 | M4: 0.64 | N4: 0.64 | O4: 0.28 | P4: 0.21 | Q4: 0.16 | R4: 0.11 | S4: 0.24 | T4: 0.91 | U4: 0.35 | V4: 1.21 | W4: 0.98 | X4: 0.81 | Y4: 0.57 | Z4: 0.45 | AA4: 0.61 | AB4: 0.38 | AC4: 0.26 | AD4: 24662 | AE4: 37454 | AF4: 37903 | AG4: 47190 | AH4: 44974 | AI4: 13532 | AJ4: 34285 | AK4: 53313 | AL4: 4272 | AM4: 27492 | AN4: 43898 | AO4: 38795 | AP4: 42932 | AQ4: 35118 | AR4: 7000 | AS4: 3000 | AT4: 7000 | AU4: 8300 | AV4: 2800 | AW4: 3100 | AX4: 5500 | AY4: 4400 | AZ4: 3500 | BA4: 5200
A5: 2025 | B5: APR | C5: 36840 | D5: 23340 | E5: 36425 | F5: 33470 | G5: 30730 | H5: 0.36 | I5: 0.45 | J5: 0.19 | K5: 160805 | L5: 120000 | M5: 0.4 | N5: 0.24 | O5: 0.31 | P5: 0.3 | Q5: 0.12 | R5: 0.07 | S5: 0.2 | T5: 1.24 | U5: 1.06 | V5: 1.08 | W5: 0.91 | X5: 1.07 | Y5: 0.26 | Z5: 0.31 | AA5: 0.56 | AB5: 0.7 | AC5: 0.3 | AD5: 28363 | AE5: 32559 | AF5: 2859 | AG5: 44682 | AH5: 89111 | AI5: 8141 | AJ5: 34285 | AK5: 19542 | AL5: 42659 | AM5: 40003 | AN5: 20115 | AO5: 40007 | AP5: 40200 | AQ5: 33754 | AR5: 6700 | AS5: 5700 | AT5: 4500 | AU5: 5000 | AV5: 2700 | AW5: 5900 | AX5: 6100 | AY5: 5500 | AZ5: 3500 | BA5: 6100
A6: 2025 | B6: MAY | C6: 64590 | D6: 41860 | E6: 49940 | F6: 34330 | G6: 29460 | H6: 0.36 | I6: 0.4 | J6: 0.24 | K6: 220180 | L6: 120000 | M6: 0.2 | N6: 0.25 | O6: 0.31 | P6: 0.22 | Q6: 0.13 | R6: 0.14 | S6: 0.2 | T6: 0.94 | U6: 0.99 | V6: 0.77 | W6: 1.02 | X6: 0.76 | Y6: 0.3 | Z6: 0.59 | AA6: 0.31 | AB6: 0.73 | AC6: 0.55 | AD6: 6097 | AE6: 46394 | AF6: 56704 | AG6: 18425 | AH6: 17854 | AI6: 60241 | AJ6: 34285 | AK6: 48037 | AL6: 41586 | AM6: 31950 | AN6: 44847 | AO6: 8193 | AP6: 43737 | AQ6: 36390 | AR6: 8900 | AS6: 3400 | AT6: 2900 | AU6: 4000 | AV6: 4500 | AW6: 3500 | AX6: 5400 | AY6: 4200 | AZ6: 2900 | BA6: 6600
A7: 2025 | B7: JUN | C7: 76530 | D7: 54200 | E7: 45950 | F7: 42900 | G7: 34960 | H7: 0.38 | I7: 0.5 | J7: 0.12 | K7: 254540 | L7: 120000 | M7: 0.44 | N7: 0.69 | O7: 0.35 | P7: 0.21 | Q7: 0.16 | R7: 0.08 | S7: 0.2 | T7: 1.1 | U7: 1.25 | V7: 0.85 | W7: 1.31 | X7: 0.94 | Y7: 0.59 | Z7: 0.56 | AA7: 0.7 | AB7: 0.73 | AC7: 0.39 | AD7: 23965 | AE7: 47071 | AF7: 30345 | AG7: 36671 | AH7: 54945 | AI7: 12717 | AJ7: 34286 | AK7: 31971 | AL7: 45318 | AM7: 39555 | AN7: 45223 | AO7: 16585 | AP7: 43065 | AQ7: 36953 | AR7: 6200 | AS7: 3200 | AT7: 4200 | AU7: 3100 | AV7: 4900 | AW7: 4000 | AX7: 4600 | AY7: 5500 | AZ7: 5200 | BA7: 3800
A8: 2025 | B8: JUL | C8: 84020 | D8: 53040 | E8: 54240 | F8: 32710 | G8: 30170 | H8: 0.37 | I8: 0.48 | J8: 0.15 | K8: 254180 | L8: 120000 | M8: 0.24 | N8: 0.41 | O8: 0.31 | P8: 0.2 | Q8: 0.16 | R8: 0.11 | S8: 0.22 | T8: 0.37 | U8: 0.46 | V8: 0.68 | W8: 1.24 | X8: 0.88 | Y8: 0.52 | Z8: 0.61 | AA8: 0.34 | AB8: 0.48 | AC8: 0.33 | AD8: 33952 | AE8: 59758 | AF8: 23186 | AG8: 5088 | AH8: 15481 | AI8: 68250 | AJ8: 34285 | AK8: 73225 | AL8: 82752 | AM8: 6957 | AN8: 11539 | AO8: 18644 | AP8: 7222 | AQ8: 33391 | AR8: 4900 | AS8: 4800 | AT8: 2300 | AU8: 2700 | AV8: 4700 | AW8: 4100 | AX8: 3400 | AY8: 4700 | AZ8: 4800 | BA8: 2500
A9: 2025 | B9: AUG | C9: 84170 | D9: 49190 | E9: 50140 | F9: 41480 | G9: 28310 | H9: 0.37 | I9: 0.44 | J9: 0.19 | K9: 253290 | L9: 120000 | M9: 0.75 | N9: 0.6 | O9: 0.34 | P9: 0.26 | Q9: 0.17 | R9: 0.12 | S9: 0.11 | T9: 0.53 | U9: 1.05 | V9: 0.59 | W9: 0.44 | X9: 0.64 | Y9: 0.51 | Z9: 0.29 | AA9: 0.3 | AB9: 0.41 | AC9: 0.32 | AD9: 44592 | AE9: 48774 | AF9: 27775 | AG9: 25626 | AH9: 32862 | AI9: 26085 | AJ9: 34286 | AK9: 56058 | AL9: 49917 | AM9: 48765 | AN9: 42341 | AO9: 4345 | AP9: 13391 | AQ9: 35803 | AR9: 7900 | AS9: 5400 | AT9: 5800 | AU9: 4800 | AV9: 3300 | AW9: 4300 | AX9: 5100 | AY9: 3000 | AZ9: 2200 | BA9: 7000
A10: 2025 | B10: SEP | C10: 78630 | D10: 41370 | E10: 53770 | F10: 37090 | G10: 31990 | H10: 0.37 | I10: 0.44 | J10: 0.19 | K10: 242850 | L10: 120000 | M10: 0.73 | N10: 0.5 | O10: 0.33 | P10: 0.21 | Q10: 0.17 | R10: 0.11 | S10: 0.18 | T10: 0.74 | U10: 0.45 | V10: 1.24 | W10: 0.38 | X10: 1.06 | Y10: 0.72 | Z10: 0.42 | AA10: 0.38 | AB10: 0.74 | AC10: 0.49 | AD10: 41608 | AE10: 38687 | AF10: 32685 | AG10: 40758 | AH10: 15259 | AI10: 36718 | AJ10: 34285 | AK10: 17916 | AL10: 14439 | AM10: 6383 | AN10: 47775 | AO10: 68781 | AP10: 62626 | AQ10: 36320 | AR10: 6900 | AS10: 5400 | AT10: 3400 | AU10: 4800 | AV10: 4500 | AW10: 4200 | AX10: 5400 | AY10: 6000 | AZ10: 5200 | BA10: 5600
A11: 2025 | B11: OCT | C11: 60760 | D11: 50950 | E11: 53140 | F11: 38170 | G11: 34660 | H11: 0.39 | I11: 0.54 | J11: 0.07 | K11: 237680 | L11: 120000 | M11: 0.72 | N11: 0.47 | O11: 0.28 | P11: 0.21 | Q11: 0.13 | R11: 0.05 | S11: 0.33 | T11: 0.62 | U11: 0.87 | V11: 1.18 | W11: 0.38 | X11: 0.36 | Y11: 0.35 | Z11: 0.45 | AA11: 0.63 | AB11: 0.61 | AC11: 0.53 | AD11: 55756 | AE11: 73802 | AF11: 10991 | AG11: 7018 | AH11: 46491 | AI11: 11657 | AJ11: 34285 | AK11: 30546 | AL11: 14673 | AM11: 18630 | AN11: 49112 | AO11: 49019 | AP11: 29146 | AQ11: 31854 | AR11: 9700 | AS11: 2900 | AT11: 4600 | AU11: 5300 | AV11: 6000 | AW11: 3500 | AX11: 6500 | AY11: 2400 | AZ11: 5900 | BA11: 3000
A12: 2025 | B12: NOV | C12: 44165 | D12: 37275 | E12: 37120 | F12: 44480 | G12: 34330 | H12: 0.38 | I12: 0.45 | J12: 0.17 | K12: 197370 | L12: 120000 | M12: 0.73 | N12: 0.75 | O12: 0.25 | P12: 0.22 | Q12: 0.15 | R12: 0.07 | S12: 0.31 | T12: 0.63 | U12: 0.97 | V12: 0.82 | W12: 1.07 | X12: 0.72 | Y12: 0.61 | Z12: 0.4 | AA12: 0.68 | AB12: 0.39 | AC12: 0.63 | AD12: 41610 | AE12: 2642 | AF12: 48284 | AG12: 17938 | AH12: 48687 | AI12: 46554 | AJ12: 34285 | AK12: 58809 | AL12: 44756 | AM12: 6109 | AN12: 24468 | AO12: 33398 | AP12: 49565 | AQ12: 36185 | AR12: 5400 | AS12: 4700 | AT12: 3500 | AU12: 6000 | AV12: 4900 | AW12: 4800 | AX12: 2600 | AY12: 7500 | AZ12: 4300 | BA12: 6200
A13: 2025 | B13: DEC | C13: 21930 | D13: 14850 | E13: 11285 | F13: 27630 | G13: 22700 | H13: 0.4 | I13: 0.54 | J13: 0.06 | K13: 98395 | L13: 120000 | M13: 0.36 | N13: 0.28 | O13: 0.3 | P13: 0.24 | Q13: 0.15 | R13: 0.15 | S13: 0.16 | T13: 0.71 | U13: 0.8 | V13: 0.57 | W13: 0.39 | X13: 0.61 | Y13: 0.72 | Z13: 0.58 | AA13: 0.65 | AB13: 0.49 | AC13: 0.57 | AD13: 45691 | AE13: 60215 | AF13: 19839 | AG13: 13621 | AH13: 59767 | AI13: 6581 | AJ13: 34286 | AK13: 42222 | AL13: 4090 | AM13: 39033 | AN13: 58269 | AO13: 68482 | AP13: 58702 | AQ13: 45132 | AR13: 8700 | AS13: 3600 | AT13: 4700 | AU13: 6500 | AV13: 4500 | AW13: 4900 | AX13: 4700 | AY13: 6700 | AZ13: 3600 | BA13: 3200
... A49: 2028 | B49: DEC | C49: 62575 | D49: 70425 | E49: 52725 | F49: 79400 | G49: 66650 | H49: 0.36 | I49: 0.48 | J49: 0.16 | K49: 331775 | L49: 250000 | M49: 0.22 | N49: 0.45 | O49: 0.33 | P49: 0.25 | Q49: 0.15 | R49: 0.05 | S49: 0.22 | T49: 1.04 | U49: 0.95 | V49: 0.63 | W49: 0.55 | X49: 1.26 | Y49: 0.63 | Z49: 0.69 | AA49: 0.6 | AB49: 0.28 | AC49: 0.29 | AD49: 62859 | AE49: 117796 | AF49: 118263 | AG49: 667 | AH49: 74945 | AI49: 54042 | AJ49: 71428 | AK49: 52446 | AL49: 92341 | AM49: 76327 | AN49: 33912 | AO49: 95373 | AP49: 93173 | AQ49: 73928 | AR49: 3100 | AS49: 3900 | AT49: 7100 | AU49: 4600 | AV49: 4800 | AW49: 7400 | AX49: 4300 | AY49: 4400 | AZ49: 5800 | BA49: 4300
X50: 1.09
X51: 1.26

Sheet Attendance_Data
A1: Fully Automatic Attendance Dashboard Source Data | O1: Daily Attendance Trend
A2: Emp_ID | B2: Emp_Name | C2: Gender | D2: Department | E2: Joining Date | F2: Total Days | G2: Present | H2: Holiday | I2: Week Off | J2: Absent | K2: Attendance % | O2: Date | P2: Present | Q2: Absent
A3: =[1]!tblEmployee[[#This Row],[Emp_ID]] -> #REF! | B3: =VLOOKUP($A3,[1]!tblEmployee[#All],MATCH([1]Attendance_Data!B$2,[1]!tblEmployee[#Headers],0),FALSE) -> #REF! | C3: =VLOOKUP($A3,[1]!tblEmployee[#All],MATCH([1]Attendance_Data!C$2,[1]!tblEmployee[#Headers],0),FALSE) -> #REF! | D3: =VLOOKUP($A3,[1]!tblEmployee[#All],MATCH([1]Attendance_Data!D$2,[1]!tblEmployee[#Headers],0),FALSE) -> #REF! | E3: =VLOOKUP($A3,[1]!tblEmployee[#All],MATCH([1]Attendance_Data!E$2,[1]!tblEmployee[#Headers],0),FALSE) -> #REF! | F3: =VLOOKUP($A3,'ATTENDANCE DATA'!$A$4:$AL$706,MATCH([1]Attendance_Data!F$2,'ATTENDANCE DATA'!$A$4:$AL$4,0),FALSE) -> #REF! | G3: =VLOOKUP($A3,'ATTENDANCE DATA'!$A$4:$AL$706,MATCH([1]Attendance_Data!G$2,'ATTENDANCE DATA'!$A$4:$AL$4,0),FALSE) -> #REF! | H3: =VLOOKUP($A3,'ATTENDANCE DATA'!$A$4:$AL$706,MATCH([1]Attendance_Data!H$2,'ATTENDANCE DATA'!$A$4:$AL$4,0),FALSE) -> #REF! | I3: =VLOOKUP($A3,'ATTENDANCE DATA'!$A$4:$AL$706,MATCH([1]Attendance_Data!I$2,'ATTENDANCE DATA'!$A$4:$AL$4,0),FALSE) -> #REF! | J3: =VLOOKUP($A3,'ATTENDANCE DATA'!$A$4:$AL$706,MATCH([1]Attendance_Data!J$2,'ATTENDANCE DATA'!$A$4:$AL$4,0),FALSE) -> #REF! | K3: =IF((G3+J3)=0,0,G3/(G3+J3)) -> #REF! | O3: ='ATTENDANCE DATA'!C4 -> 46174 | P3: =COUNTIF('ATTENDANCE DATA'!C7:C706,"P") -> 572 | Q3: =COUNTIF('ATTENDANCE DATA'!C7:C706,"A") -> 128
A4: =[1]!tblEmployee[[#This Row],[Emp_ID]] -> #REF! | B4: =VLOOKUP($A4,[1]!tblEmployee[#All],MATCH([1]Attendance_Data!B$2,[1]!tblEmployee[#Headers],0),FALSE) -> #REF! | C4: =VLOOKUP($A4,[1]!tblEmployee[#All],MATCH([1]Attendance_Data!C$2,[1]!tblEmployee[#Headers],0),FALSE) -> #REF! | D4: =VLOOKUP($A4,[1]!tblEmployee[#All],MATCH([1]Attendance_Data!D$2,[1]!tblEmployee[#Headers],0),FALSE) -> #REF! | E4: =VLOOKUP($A4,[1]!tblEmployee[#All],MATCH([1]Attendance_Data!E$2,[1]!tblEmployee[#Headers],0),FALSE) -> #REF! | F4: =VLOOKUP($A4,'ATTENDANCE DATA'!$A$4:$AL$706,MATCH([1]Attendance_Data!F$2,'ATTENDANCE DATA'!$A$4:$AL$4,0),FALSE) -> #REF! | G4: =VLOOKUP($A4,'ATTENDANCE DATA'!$A$4:$AL$706,MATCH([1]Attendance_Data!G$2,'ATTENDANCE DATA'!$A$4:$AL$4,0),FALSE) -> #REF! | H4: =VLOOKUP($A4,'ATTENDANCE DATA'!$A$4:$AL$706,MATCH([1]Attendance_Data!H$2,'ATTENDANCE DATA'!$A$4:$AL$4,0),FALSE) -> #REF! | I4: =VLOOKUP($A4,'ATTENDANCE DATA'!$A$4:$AL$706,MATCH([1]Attendance_Data!I$2,'ATTENDANCE DATA'!$A$4:$AL$4,0),FALSE) -> #REF! | J4: =VLOOKUP($A4,'ATTENDANCE DATA'!$A$4:$AL$706,MATCH([1]Attendance_Data!J$2,'ATTENDANCE DATA'!$A$4:$AL$4,0),FALSE) -> #REF! | K4: =IF((G4+J4)=0,0,G4/(G4+J4)) -> #REF! | O4: ='ATTENDANCE DATA'!D4 -> 46175 | P4: =COUNTIF('ATTENDANCE DATA'!D7:D706,"P") -> 557 | Q4: =COUNTIF('ATTENDANCE DATA'!D7:D706,"A") -> 143
A5: =[1]!tblEmployee[[#This Row],[Emp_ID]] -> #REF! | B5: =VLOOKUP($A5,[1]!tblEmployee[#All],MATCH([1]Attendance_Data!B$2,[1]!tblEmployee[#Headers],0),FALSE) -> #REF! | C5: =VLOOKUP($A5,[1]!tblEmployee[#All],MATCH([1]Attendance_Data!C$2,[1]!tblEmployee[#Headers],0),FALSE) -> #REF! | D5: =VLOOKUP($A5,[1]!tblEmployee[#All],MATCH([1]Attendance_Data!D$2,[1]!tblEmployee[#Headers],0),FALSE) -> #REF! | E5: =VLOOKUP($A5,[1]!tblEmployee[#All],MATCH([1]Attendance_Data!E$2,[1]!tblEmployee[#Headers],0),FALSE) -> #REF! | F5: =VLOOKUP($A5,'ATTENDANCE DATA'!$A$4:$AL$706,MATCH([1]Attendance_Data!F$2,'ATTENDANCE DATA'!$A$4:$AL$4,0),FALSE) -> #REF! | G5: =VLOOKUP($A5,'ATTENDANCE DATA'!$A$4:$AL$706,MATCH([1]Attendance_Data!G$2,'ATTENDANCE DATA'!$A$4:$AL$4,0),FALSE) -> #REF! | H5: =VLOOKUP($A5,'ATTENDANCE DATA'!$A$4:$AL$706,MATCH([1]Attendance_Data!H$2,'ATTENDANCE DATA'!$A$4:$AL$4,0),FALSE) -> #REF! | I5: =VLOOKUP($A5,'ATTENDANCE DATA'!$A$4:$AL$706,MATCH([1]Attendance_Data!I$2,'ATTENDANCE DATA'!$A$4:$AL$4,0),FALSE) -> #REF! | J5: =VLOOKUP($A5,'ATTENDANCE DATA'!$A$4:$AL$706,MATCH([1]Attendance_Data!J$2,'ATTENDANCE DATA'!$A$4:$AL$4,0),FALSE) -> #REF! | K5: =IF((G5+J5)=0,0,G5/(G5+J5)) -> #REF! | O5: ='ATTENDANCE DATA'!E4 -> 46176 | P5: =COUNTIF('ATTENDANCE DATA'!E7:E706,"P") -> 576 | Q5: =COUNTIF('ATTENDANCE DATA'!E7:E706,"A") -> 124
A6: =[1]!tblEmployee[[#This Row],[Emp_ID]] -> #REF! | B6: =VLOOKUP($A6,[1]!tblEmployee[#All],MATCH([1]Attendance_Data!B$2,[1]!tblEmployee[#Headers],0),FALSE) -> #REF! | C6: =VLOOKUP($A6,[1]!tblEmployee[#All],MATCH([1]Attendance_Data!C$2,[1]!tblEmployee[#Headers],0),FALSE) -> #REF! | D6: =VLOOKUP($A6,[1]!tblEmployee[#All],MATCH([1]Attendance_Data!D$2,[1]!tblEmployee[#Headers],0),FALSE) -> #REF! | E6: =VLOOKUP($A6,[1]!tblEmployee[#All],MATCH([1]Attendance_Data!E$2,[1]!tblEmployee[#Headers],0),FALSE) -> #REF! | F6: =VLOOKUP($A6,'ATTENDANCE DATA'!$A$4:$AL$706,MATCH([1]Attendance_Data!F$2,'ATTENDANCE DATA'!$A$4:$AL$4,0),FALSE) -> #REF! | G6: =VLOOKUP($A6,'ATTENDANCE DATA'!$A$4:$AL$706,MATCH([1]Attendance_Data!G$2,'ATTENDANCE DATA'!$A$4:$AL$4,0),FALSE) -> #REF! | H6: =VLOOKUP($A6,'ATTENDANCE DATA'!$A$4:$AL$706,MATCH([1]Attendance_Data!H$2,'ATTENDANCE DATA'!$A$4:$AL$4,0),FALSE) -> #REF! | I6: =VLOOKUP($A6,'ATTENDANCE DATA'!$A$4:$AL$706,MATCH([1]Attendance_Data!I$2,'ATTENDANCE DATA'!$A$4:$AL$4,0),FALSE) -> #REF! | J6: =VLOOKUP($A6,'ATTENDANCE DATA'!$A$4:$AL$706,MATCH([1]Attendance_Data!J$2,'ATTENDANCE DATA'!$A$4:$AL$4,0),FALSE) -> #REF! | K6: =IF((G6+J6)=0,0,G6/(G6+J6)) -> #REF! | O6: ='ATTENDANCE DATA'!F4 -> 46177 | P6: =COUNTIF('ATTENDANCE DATA'!F7:F706,"P") -> 568 | Q6: =COUNTIF('ATTENDANCE DATA'!F7:F706,"A") -> 132
A7: =[1]!tblEmployee[[#This Row],[Emp_ID]] -> #REF! | B7: =VLOOKUP($A7,[1]!tblEmployee[#All],MATCH([1]Attendance_Data!B$2,[1]!tblEmployee[#Headers],0),FALSE) -> #REF! | C7: =VLOOKUP($A7,[1]!tblEmployee[#All],MATCH([1]Attendance_Data!C$2,[1]!tblEmployee[#Headers],0),FALSE) -> #REF! | D7: =VLOOKUP($A7,[1]!tblEmployee[#All],MATCH([1]Attendance_Data!D$2,[1]!tblEmployee[#Headers],0),FALSE) -> #REF! | E7: =VLOOKUP($A7,[1]!tblEmployee[#All],MATCH([1]Attendance_Data!E$2,[1]!tblEmployee[#Headers],0),FALSE) -> #REF! | F7: =VLOOKUP($A7,'ATTENDANCE DATA'!$A$4:$AL$706,MATCH([1]Attendance_Data!F$2,'ATTENDANCE DATA'!$A$4:$AL$4,0),FALSE) -> #REF! | G7: =VLOOKUP($A7,'ATTENDANCE DATA'!$A$4:$AL$706,MATCH([1]Attendance_Data!G$2,'ATTENDANCE DATA'!$A$4:$AL$4,0),FALSE) -> #REF! | H7: =VLOOKUP($A7,'ATTENDANCE DATA'!$A$4:$AL$706,MATCH([1]Attendance_Data!H$2,'ATTENDANCE DATA'!$A$4:$AL$4,0),FALSE) -> #REF! | I7: =VLOOKUP($A7,'ATTENDANCE DATA'!$A$4:$AL$706,MATCH([1]Attendance_Data!I$2,'ATTENDANCE DATA'!$A$4:$AL$4,0),FALSE) -> #REF! | J7: =VLOOKUP($A7,'ATTENDANCE DATA'!$A$4:$AL$706,MATCH([1]Attendance_Data!J$2,'ATTENDANCE DATA'!$A$4:$AL$4,0),FALSE) -> #REF! | K7: =IF((G7+J7)=0,0,G7/(G7+J7)) -> #REF! | O7: ='ATTENDANCE DATA'!G4 -> 46178 | P7: =COUNTIF('ATTENDANCE DATA'!G7:G706,"P") -> 588 | Q7: =COUNTIF('ATTENDANCE DATA'!G7:G706,"A") -> 112
A8: =[1]!tblEmployee[[#This Row],[Emp_ID]] -> #REF! | B8: =VLOOKUP($A8,[1]!tblEmployee[#All],MATCH([1]Attendance_Data!B$2,[1]!tblEmployee[#Headers],0),FALSE) -> #REF! | C8: =VLOOKUP($A8,[1]!tblEmployee[#All],MATCH([1]Attendance_Data!C$2,[1]!tblEmployee[#Headers],0),FALSE) -> #REF! | D8: =VLOOKUP($A8,[1]!tblEmployee[#All],MATCH([1]Attendance_Data!D$2,[1]!tblEmployee[#Headers],0),FALSE) -> #REF! | E8: =VLOOKUP($A8,[1]!tblEmployee[#All],MATCH([1]Attendance_Data!E$2,[1]!tblEmployee[#Headers],0),FALSE) -> #REF! | F8: =VLOOKUP($A8,'ATTENDANCE DATA'!$A$4:$AL$706,MATCH([1]Attendance_Data!F$2,'ATTENDANCE DATA'!$A$4:$AL$4,0),FALSE) -> #REF! | G8: =VLOOKUP($A8,'ATTENDANCE DATA'!$A$4:$AL$706,MATCH([1]Attendance_Data!G$2,'ATTENDANCE DATA'!$A$4:$AL$4,0),FALSE) -> #REF! | H8: =VLOOKUP($A8,'ATTENDANCE DATA'!$A$4:$AL$706,MATCH([1]Attendance_Data!H$2,'ATTENDANCE DATA'!$A$4:$AL$4,0),FALSE) -> #REF! | I8: =VLOOKUP($A8,'ATTENDANCE DATA'!$A$4:$AL$706,MATCH([1]Attendance_Data!I$2,'ATTENDANCE DATA'!$A$4:$AL$4,0),FALSE) -> #REF! | J8: =VLOOKUP($A8,'ATTENDANCE DATA'!$A$4:$AL$706,MATCH([1]Attendance_Data!J$2,'ATTENDANCE DATA'!$A$4:$AL$4,0),FALSE) -> #REF! | K8: =IF((G8+J8)=0,0,G8/(G8+J8)) -> #REF! | O8: ='ATTENDANCE DATA'!H4 -> 46179 | P8: =COUNTIF('ATTENDANCE DATA'!H7:H706,"P") -> 571 | Q8: =COUNTIF('ATTENDANCE DATA'!H7:H706,"A") -> 129
A9: =[1]!tblEmployee[[#This Row],[Emp_ID]] -> #REF! | B9: =VLOOKUP($A9,[1]!tblEmployee[#All],MATCH([1]Attendance_Data!B$2,[1]!tblEmployee[#Headers],0),FALSE) -> #REF! | C9: =VLOOKUP($A9,[1]!tblEmployee[#All],MATCH([1]Attendance_Data!C$2,[1]!tblEmployee[#Headers],0),FALSE) -> #REF! | D9: =VLOOKUP($A9,[1]!tblEmployee[#All],MATCH([1]Attendance_Data!D$2,[1]!tblEmployee[#Headers],0),FALSE) -> #REF! | E9: =VLOOKUP($A9,[1]!tblEmployee[#All],MATCH([1]Attendance_Data!E$2,[1]!tblEmployee[#Headers],0),FALSE) -> #REF! | F9: =VLOOKUP($A9,'ATTENDANCE DATA'!$A$4:$AL$706,MATCH([1]Attendance_Data!F$2,'ATTENDANCE DATA'!$A$4:$AL$4,0),FALSE) -> #REF! | G9: =VLOOKUP($A9,'ATTENDANCE DATA'!$A$4:$AL$706,MATCH([1]Attendance_Data!G$2,'ATTENDANCE DATA'!$A$4:$AL$4,0),FALSE) -> #REF! | H9: =VLOOKUP($A9,'ATTENDANCE DATA'!$A$4:$AL$706,MATCH([1]Attendance_Data!H$2,'ATTENDANCE DATA'!$A$4:$AL$4,0),FALSE) -> #REF! | I9: =VLOOKUP($A9,'ATTENDANCE DATA'!$A$4:$AL$706,MATCH([1]Attendance_Data!I$2,'ATTENDANCE DATA'!$A$4:$AL$4,0),FALSE) -> #REF! | J9: =VLOOKUP($A9,'ATTENDANCE DATA'!$A$4:$AL$706,MATCH([1]Attendance_Data!J$2,'ATTENDANCE DATA'!$A$4:$AL$4,0),FALSE) -> #REF! | K9: =IF((G9+J9)=0,0,G9/(G9+J9)) -> #REF! | O9: ='ATTENDANCE DATA'!I4 -> 46180 | P9: =COUNTIF('ATTENDANCE DATA'!I7:I706,"P") -> 0 | Q9: =COUNTIF('ATTENDANCE DATA'!I7:I706,"A") -> 0
A10: =[1]!tblEmployee[[#This Row],[Emp_ID]] -> #REF! | B10: =VLOOKUP($A10,[1]!tblEmployee[#All],MATCH([1]Attendance_Data!B$2,[1]!tblEmployee[#Headers],0),FALSE) -> #REF! | C10: =VLOOKUP($A10,[1]!tblEmployee[#All],MATCH([1]Attendance_Data!C$2,[1]!tblEmployee[#Headers],0),FALSE) -> #REF! | D10: =VLOOKUP($A10,[1]!tblEmployee[#All],MATCH([1]Attendance_Data!D$2,[1]!tblEmployee[#Headers],0),FALSE) -> #REF! | E10: =VLOOKUP($A10,[1]!tblEmployee[#All],MATCH([1]Attendance_Data!E$2,[1]!tblEmployee[#Headers],0),FALSE) -> #REF! | F10: =VLOOKUP($A10,'ATTENDANCE DATA'!$A$4:$AL$706,MATCH([1]Attendance_Data!F$2,'ATTENDANCE DATA'!$A$4:$AL$4,0),FALSE) -> #REF! | G10: =VLOOKUP($A10,'ATTENDANCE DATA'!$A$4:$AL$706,MATCH([1]Attendance_Data!G$2,'ATTENDANCE DATA'!$A$4:$AL$4,0),FALSE) -> #REF! | H10: =VLOOKUP($A10,'ATTENDANCE DATA'!$A$4:$AL$706,MATCH([1]Attendance_Data!H$2,'ATTENDANCE DATA'!$A$4:$AL$4,0),FALSE) -> #REF! | I10: =VLOOKUP($A10,'ATTENDANCE DATA'!$A$4:$AL$706,MATCH([1]Attendance_Data!I$2,'ATTENDANCE DATA'!$A$4:$AL$4,0),FALSE) -> #REF! | J10: =VLOOKUP($A10,'ATTENDANCE DATA'!$A$4:$AL$706,MATCH([1]Attendance_Data!J$2,'ATTENDANCE DATA'!$A$4:$AL$4,0),FALSE) -> #REF! | K10: =IF((G10+J10)=0,0,G10/(G10+J10)) -> #REF! | O10: ='ATTENDANCE DATA'!J4 -> 46181 | P10: =COUNTIF('ATTENDANCE DATA'!J7:J706,"P") -> 572 | Q10: =COUNTIF('ATTENDANCE DATA'!J7:J706,"A") -> 128
A11: =[1]!tblEmployee[[#This Row],[Emp_ID]] -> #REF! | B11: =VLOOKUP($A11,[1]!tblEmployee[#All],MATCH([1]Attendance_Data!B$2,[1]!tblEmployee[#Headers],0),FALSE) -> #REF! | C11: =VLOOKUP($A11,[1]!tblEmployee[#All],MATCH([1]Attendance_Data!C$2,[1]!tblEmployee[#Headers],0),FALSE) -> #REF! | D11: =VLOOKUP($A11,[1]!tblEmployee[#All],MATCH([1]Attendance_Data!D$2,[1]!tblEmployee[#Headers],0),FALSE) -> #REF! | E11: =VLOOKUP($A11,[1]!tblEmployee[#All],MATCH([1]Attendance_Data!E$2,[1]!tblEmployee[#Headers],0),FALSE) -> #REF! | F11: =VLOOKUP($A11,'ATTENDANCE DATA'!$A$4:$AL$706,MATCH([1]Attendance_Data!F$2,'ATTENDANCE DATA'!$A$4:$AL$4,0),FALSE) -> #REF! | G11: =VLOOKUP($A11,'ATTENDANCE DATA'!$A$4:$AL$706,MATCH([1]Attendance_Data!G$2,'ATTENDANCE DATA'!$A$4:$AL$4,0),FALSE) -> #REF! | H11: =VLOOKUP($A11,'ATTENDANCE DATA'!$A$4:$AL$706,MATCH([1]Attendance_Data!H$2,'ATTENDANCE DATA'!$A$4:$AL$4,0),FALSE) -> #REF! | I11: =VLOOKUP($A11,'ATTENDANCE DATA'!$A$4:$AL$706,MATCH([1]Attendance_Data!I$2,'ATTENDANCE DATA'!$A$4:$AL$4,0),FALSE) -> #REF! | J11: =VLOOKUP($A11,'ATTENDANCE DATA'!$A$4:$AL$706,MATCH([1]Attendance_Data!J$2,'ATTENDANCE DATA'!$A$4:$AL$4,0),FALSE) -> #REF! | K11: =IF((G11+J11)=0,0,G11/(G11+J11)) -> #REF! | O11: ='ATTENDANCE DATA'!K4 -> 46182 | P11: =COUNTIF('ATTENDANCE DATA'!K7:K706,"P") -> 561 | Q11: =COUNTIF('ATTENDANCE DATA'!K7:K706,"A") -> 139
A12: =[1]!tblEmployee[[#This Row],[Emp_ID]] -> #REF! | B12: =VLOOKUP($A12,[1]!tblEmployee[#All],MATCH([1]Attendance_Data!B$2,[1]!tblEmployee[#Headers],0),FALSE) -> #REF! | C12: =VLOOKUP($A12,[1]!tblEmployee[#All],MATCH([1]Attendance_Data!C$2,[1]!tblEmployee[#Headers],0),FALSE) -> #REF! | D12: =VLOOKUP($A12,[1]!tblEmployee[#All],MATCH([1]Attendance_Data!D$2,[1]!tblEmployee[#Headers],0),FALSE) -> #REF! | E12: =VLOOKUP($A12,[1]!tblEmployee[#All],MATCH([1]Attendance_Data!E$2,[1]!tblEmployee[#Headers],0),FALSE) -> #REF! | F12: =VLOOKUP($A12,'ATTENDANCE DATA'!$A$4:$AL$706,MATCH([1]Attendance_Data!F$2,'ATTENDANCE DATA'!$A$4:$AL$4,0),FALSE) -> #REF! | G12: =VLOOKUP($A12,'ATTENDANCE DATA'!$A$4:$AL$706,MATCH([1]Attendance_Data!G$2,'ATTENDANCE DATA'!$A$4:$AL$4,0),FALSE) -> #REF! | H12: =VLOOKUP($A12,'ATTENDANCE DATA'!$A$4:$AL$706,MATCH([1]Attendance_Data!H$2,'ATTENDANCE DATA'!$A$4:$AL$4,0),FALSE) -> #REF! | I12: =VLOOKUP($A12,'ATTENDANCE DATA'!$A$4:$AL$706,MATCH([1]Attendance_Data!I$2,'ATTENDANCE DATA'!$A$4:$AL$4,0),FALSE) -> #REF! | J12: =VLOOKUP($A12,'ATTENDANCE DATA'!$A$4:$AL$706,MATCH([1]Attendance_Data!J$2,'ATTENDANCE DATA'!$A$4:$AL$4,0),FALSE) -> #REF! | K12: =IF((G12+J12)=0,0,G12/(G12+J12)) -> #REF! | O12: ='ATTENDANCE DATA'!L4 -> 46183 | P12: =COUNTIF('ATTENDANCE DATA'!L7:L706,"P") -> 0 | Q12: =COUNTIF('ATTENDANCE DATA'!L7:L706,"A") -> 0
A13: =[1]!tblEmployee[[#This Row],[Emp_ID]] -> #REF! | B13: =VLOOKUP($A13,[1]!tblEmployee[#All],MATCH([1]Attendance_Data!B$2,[1]!tblEmployee[#Headers],0),FALSE) -> #REF! | C13: =VLOOKUP($A13,[1]!tblEmployee[#All],MATCH([1]Attendance_Data!C$2,[1]!tblEmployee[#Headers],0),FALSE) -> #REF! | D13: =VLOOKUP($A13,[1]!tblEmployee[#All],MATCH([1]Attendance_Data!D$2,[1]!tblEmployee[#Headers],0),FALSE) -> #REF! | E13: =VLOOKUP($A13,[1]!tblEmployee[#All],MATCH([1]Attendance_Data!E$2,[1]!tblEmployee[#Headers],0),FALSE) -> #REF! | F13: =VLOOKUP($A13,'ATTENDANCE DATA'!$A$4:$AL$706,MATCH([1]Attendance_Data!F$2,'ATTENDANCE DATA'!$A$4:$AL$4,0),FALSE) -> #REF! | G13: =VLOOKUP($A13,'ATTENDANCE DATA'!$A$4:$AL$706,MATCH([1]Attendance_Data!G$2,'ATTENDANCE DATA'!$A$4:$AL$4,0),FALSE) -> #REF! | H13: =VLOOKUP($A13,'ATTENDANCE DATA'!$A$4:$AL$706,MATCH([1]Attendance_Data!H$2,'ATTENDANCE DATA'!$A$4:$AL$4,0),FALSE) -> #REF! | I13: =VLOOKUP($A13,'ATTENDANCE DATA'!$A$4:$AL$706,MATCH([1]Attendance_Data!I$2,'ATTENDANCE DATA'!$A$4:$AL$4,0),FALSE) -> #REF! | J13: =VLOOKUP($A13,'ATTENDANCE DATA'!$A$4:$AL$706,MATCH([1]Attendance_Data!J$2,'ATTENDANCE DATA'!$A$4:$AL$4,0),FALSE) -> #REF! | K13: =IF((G13+J13)=0,0,G13/(G13+J13)) -> #REF! | O13: ='ATTENDANCE DATA'!M4 -> 46184 | P13: =COUNTIF('ATTENDANCE DATA'!M7:M706,"P") -> 566 | Q13: =COUNTIF('ATTENDANCE DATA'!M7:M706,"A") -> 134
A14: =[1]!tblEmployee[[#This Row],[Emp_ID]] -> #REF! | B14: =VLOOKUP($A14,[1]!tblEmployee[#All],MATCH([1]Attendance_Data!B$2,[1]!tblEmployee[#Headers],0),FALSE) -> #REF! | C14: =VLOOKUP($A14,[1]!tblEmployee[#All],MATCH([1]Attendance_Data!C$2,[1]!tblEmployee[#Headers],0),FALSE) -> #REF! | D14: =VLOOKUP($A14,[1]!tblEmployee[#All],MATCH([1]Attendance_Data!D$2,[1]!tblEmployee[#Headers],0),FALSE) -> #REF! | E14: =VLOOKUP($A14,[1]!tblEmployee[#All],MATCH([1]Attendance_Data!E$2,[1]!tblEmployee[#Headers],0),FALSE) -> #REF! | F14: =VLOOKUP($A14,'ATTENDANCE DATA'!$A$4:$AL$706,MATCH([1]Attendance_Data!F$2,'ATTENDANCE DATA'!$A$4:$AL$4,0),FALSE) -> #REF! | G14: =VLOOKUP($A14,'ATTENDANCE DATA'!$A$4:$AL$706,MATCH([1]Attendance_Data!G$2,'ATTENDANCE DATA'!$A$4:$AL$4,0),FALSE) -> #REF! | H14: =VLOOKUP($A14,'ATTENDANCE DATA'!$A$4:$AL$706,MATCH([1]Attendance_Data!H$2,'ATTENDANCE DATA'!$A$4:$AL$4,0),FALSE) -> #REF! | I14: =VLOOKUP($A14,'ATTENDANCE DATA'!$A$4:$AL$706,MATCH([1]Attendance_Data!I$2,'ATTENDANCE DATA'!$A$4:$AL$4,0),FALSE) -> #REF! | J14: =VLOOKUP($A14,'ATTENDANCE DATA'!$A$4:$AL$706,MATCH([1]Attendance_Data!J$2,'ATTENDANCE DATA'!$A$4:$AL$4,0),FALSE) -> #REF! | K14: =IF((G14+J14)=0,0,G14/(G14+J14)) -> #REF! | O14: ='ATTENDANCE DATA'!N4 -> 46185 | P14: =COUNTIF('ATTENDANCE DATA'!N7:N706,"P") -> 561 | Q14: =COUNTIF('ATTENDANCE DATA'!N7:N706,"A") -> 139
A15: =[1]!tblEmployee[[#This Row],[Emp_ID]] -> #REF! | B15: =VLOOKUP($A15,[1]!tblEmployee[#All],MATCH([1]Attendance_Data!B$2,[1]!tblEmployee[#Headers],0),FALSE) -> #REF! | C15: =VLOOKUP($A15,[1]!tblEmployee[#All],MATCH([1]Attendance_Data!C$2,[1]!tblEmployee[#Headers],0),FALSE) -> #REF! | D15: =VLOOKUP($A15,[1]!tblEmployee[#All],MATCH([1]Attendance_Data!D$2,[1]!tblEmployee[#Headers],0),FALSE) -> #REF! | E15: =VLOOKUP($A15,[1]!tblEmployee[#All],MATCH([1]Attendance_Data!E$2,[1]!tblEmployee[#Headers],0),FALSE) -> #REF! | F15: =VLOOKUP($A15,'ATTENDANCE DATA'!$A$4:$AL$706,MATCH([1]Attendance_Data!F$2,'ATTENDANCE DATA'!$A$4:$AL$4,0),FALSE) -> #REF! | G15: =VLOOKUP($A15,'ATTENDANCE DATA'!$A$4:$AL$706,MATCH([1]Attendance_Data!G$2,'ATTENDANCE DATA'!$A$4:$AL$4,0),FALSE) -> #REF! | H15: =VLOOKUP($A15,'ATTENDANCE DATA'!$A$4:$AL$706,MATCH([1]Attendance_Data!H$2,'ATTENDANCE DATA'!$A$4:$AL$4,0),FALSE) -> #REF! | I15: =VLOOKUP($A15,'ATTENDANCE DATA'!$A$4:$AL$706,MATCH([1]Attendance_Data!I$2,'ATTENDANCE DATA'!$A$4:$AL$4,0),FALSE) -> #REF! | J15: =VLOOKUP($A15,'ATTENDANCE DATA'!$A$4:$AL$706,MATCH([1]Attendance_Data!J$2,'ATTENDANCE DATA'!$A$4:$AL$4,0),FALSE) -> #REF! | K15: =IF((G15+J15)=0,0,G15/(G15+J15)) -> #REF! | O15: ='ATTENDANCE DATA'!O4 -> 46186 | P15: =COUNTIF('ATTENDANCE DATA'!O7:O706,"P") -> 562 | Q15: =COUNTIF('ATTENDANCE DATA'!O7:O706,"A") -> 138
A16: =[1]!tblEmployee[[#This Row],[Emp_ID]] -> #REF! | B16: =VLOOKUP($A16,[1]!tblEmployee[#All],MATCH([1]Attendance_Data!B$2,[1]!tblEmployee[#Headers],0),FALSE) -> #REF! | C16: =VLOOKUP($A16,[1]!tblEmployee[#All],MATCH([1]Attendance_Data!C$2,[1]!tblEmployee[#Headers],0),FALSE) -> #REF! | D16: =VLOOKUP($A16,[1]!tblEmployee[#All],MATCH([1]Attendance_Data!D$2,[1]!tblEmployee[#Headers],0),FALSE) -> #REF! | E16: =VLOOKUP($A16,[1]!tblEmployee[#All],MATCH([1]Attendance_Data!E$2,[1]!tblEmployee[#Headers],0),FALSE) -> #REF! | F16: =VLOOKUP($A16,'ATTENDANCE DATA'!$A$4:$AL$706,MATCH([1]Attendance_Data!F$2,'ATTENDANCE DATA'!$A$4:$AL$4,0),FALSE) -> #REF! | G16: =VLOOKUP($A16,'ATTENDANCE DATA'!$A$4:$AL$706,MATCH([1]Attendance_Data!G$2,'ATTENDANCE DATA'!$A$4:$AL$4,0),FALSE) -> #REF! | H16: =VLOOKUP($A16,'ATTENDANCE DATA'!$A$4:$AL$706,MATCH([1]Attendance_Data!H$2,'ATTENDANCE DATA'!$A$4:$AL$4,0),FALSE) -> #REF! | I16: =VLOOKUP($A16,'ATTENDANCE DATA'!$A$4:$AL$706,MATCH([1]Attendance_Data!I$2,'ATTENDANCE DATA'!$A$4:$AL$4,0),FALSE) -> #REF! | J16: =VLOOKUP($A16,'ATTENDANCE DATA'!$A$4:$AL$706,MATCH([1]Attendance_Data!J$2,'ATTENDANCE DATA'!$A$4:$AL$4,0),FALSE) -> #REF! | K16: =IF((G16+J16)=0,0,G16/(G16+J16)) -> #REF! | O16: ='ATTENDANCE DATA'!P4 -> 46187 | P16: =COUNTIF('ATTENDANCE DATA'!P7:P706,"P") -> 0 | Q16: =COUNTIF('ATTENDANCE DATA'!P7:P706,"A") -> 0
A17: =[1]!tblEmployee[[#This Row],[Emp_ID]] -> #REF! | B17: =VLOOKUP($A17,[1]!tblEmployee[#All],MATCH([1]Attendance_Data!B$2,[1]!tblEmployee[#Headers],0),FALSE) -> #REF! | C17: =VLOOKUP($A17,[1]!tblEmployee[#All],MATCH([1]Attendance_Data!C$2,[1]!tblEmployee[#Headers],0),FALSE) -> #REF! | D17: =VLOOKUP($A17,[1]!tblEmployee[#All],MATCH([1]Attendance_Data!D$2,[1]!tblEmployee[#Headers],0),FALSE) -> #REF! | E17: =VLOOKUP($A17,[1]!tblEmployee[#All],MATCH([1]Attendance_Data!E$2,[1]!tblEmployee[#Headers],0),FALSE) -> #REF! | F17: =VLOOKUP($A17,'ATTENDANCE DATA'!$A$4:$AL$706,MATCH([1]Attendance_Data!F$2,'ATTENDANCE DATA'!$A$4:$AL$4,0),FALSE) -> #REF! | G17: =VLOOKUP($A17,'ATTENDANCE DATA'!$A$4:$AL$706,MATCH([1]Attendance_Data!G$2,'ATTENDANCE DATA'!$A$4:$AL$4,0),FALSE) -> #REF! | H17: =VLOOKUP($A17,'ATTENDANCE DATA'!$A$4:$AL$706,MATCH([1]Attendance_Data!H$2,'ATTENDANCE DATA'!$A$4:$AL$4,0),FALSE) -> #REF! | I17: =VLOOKUP($A17,'ATTENDANCE DATA'!$A$4:$AL$706,MATCH([1]Attendance_Data!I$2,'ATTENDANCE DATA'!$A$4:$AL$4,0),FALSE) -> #REF! | J17: =VLOOKUP($A17,'ATTENDANCE DATA'!$A$4:$AL$706,MATCH([1]Attendance_Data!J$2,'ATTENDANCE DATA'!$A$4:$AL$4,0),FALSE) -> #REF! | K17: =IF((G17+J17)=0,0,G17/(G17+J17)) -> #REF! | O17: ='ATTENDANCE DATA'!Q4 -> 46188 | P17: =COUNTIF('ATTENDANCE DATA'!Q7:Q706,"P") -> 566 | Q17: =COUNTIF('ATTENDANCE DATA'!Q7:Q706,"A") -> 134
A18: =[1]!tblEmployee[[#This Row],[Emp_ID]] -> #REF! | B18: =VLOOKUP($A18,[1]!tblEmployee[#All],MATCH([1]Attendance_Data!B$2,[1]!tblEmployee[#Headers],0),FALSE) -> #REF! | C18: =VLOOKUP($A18,[1]!tblEmployee[#All],MATCH([1]Attendance_Data!C$2,[1]!tblEmployee[#Headers],0),FALSE) -> #REF! | D18: =VLOOKUP($A18,[1]!tblEmployee[#All],MATCH([1]Attendance_Data!D$2,[1]!tblEmployee[#Headers],0),FALSE) -> #REF! | E18: =VLOOKUP($A18,[1]!tblEmployee[#All],MATCH([1]Attendance_Data!E$2,[1]!tblEmployee[#Headers],0),FALSE) -> #REF! | F18: =VLOOKUP($A18,'ATTENDANCE DATA'!$A$4:$AL$706,MATCH([1]Attendance_Data!F$2,'ATTENDANCE DATA'!$A$4:$AL$4,0),FALSE) -> #REF! | G18: =VLOOKUP($A18,'ATTENDANCE DATA'!$A$4:$AL$706,MATCH([1]Attendance_Data!G$2,'ATTENDANCE DATA'!$A$4:$AL$4,0),FALSE) -> #REF! | H18: =VLOOKUP($A18,'ATTENDANCE DATA'!$A$4:$AL$706,MATCH([1]Attendance_Data!H$2,'ATTENDANCE DATA'!$A$4:$AL$4,0),FALSE) -> #REF! | I18: =VLOOKUP($A18,'ATTENDANCE DATA'!$A$4:$AL$706,MATCH([1]Attendance_Data!I$2,'ATTENDANCE DATA'!$A$4:$AL$4,0),FALSE) -> #REF! | J18: =VLOOKUP($A18,'ATTENDANCE DATA'!$A$4:$AL$706,MATCH([1]Attendance_Data!J$2,'ATTENDANCE DATA'!$A$4:$AL$4,0),FALSE) -> #REF! | K18: =IF((G18+J18)=0,0,G18/(G18+J18)) -> #REF! | O18: ='ATTENDANCE DATA'!R4 -> 46189 | P18: =COUNTIF('ATTENDANCE DATA'!R7:R706,"P") -> 561 | Q18: =COUNTIF('ATTENDANCE DATA'!R7:R706,"A") -> 139
A19: =[1]!tblEmployee[[#This Row],[Emp_ID]] -> #REF! | B19: =VLOOKUP($A19,[1]!tblEmployee[#All],MATCH([1]Attendance_Data!B$2,[1]!tblEmployee[#Headers],0),FALSE) -> #REF! | C19: =VLOOKUP($A19,[1]!tblEmployee[#All],MATCH([1]Attendance_Data!C$2,[1]!tblEmployee[#Headers],0),FALSE) -> #REF! | D19: =VLOOKUP($A19,[1]!tblEmployee[#All],MATCH([1]Attendance_Data!D$2,[1]!tblEmployee[#Headers],0),FALSE) -> #REF! | E19: =VLOOKUP($A19,[1]!tblEmployee[#All],MATCH([1]Attendance_Data!E$2,[1]!tblEmployee[#Headers],0),FALSE) -> #REF! | F19: =VLOOKUP($A19,'ATTENDANCE DATA'!$A$4:$AL$706,MATCH([1]Attendance_Data!F$2,'ATTENDANCE DATA'!$A$4:$AL$4,0),FALSE) -> #REF! | G19: =VLOOKUP($A19,'ATTENDANCE DATA'!$A$4:$AL$706,MATCH([1]Attendance_Data!G$2,'ATTENDANCE DATA'!$A$4:$AL$4,0),FALSE) -> #REF! | H19: =VLOOKUP($A19,'ATTENDANCE DATA'!$A$4:$AL$706,MATCH([1]Attendance_Data!H$2,'ATTENDANCE DATA'!$A$4:$AL$4,0),FALSE) -> #REF! | I19: =VLOOKUP($A19,'ATTENDANCE DATA'!$A$4:$AL$706,MATCH([1]Attendance_Data!I$2,'ATTENDANCE DATA'!$A$4:$AL$4,0),FALSE) -> #REF! | J19: =VLOOKUP($A19,'ATTENDANCE DATA'!$A$4:$AL$706,MATCH([1]Attendance_Data!J$2,'ATTENDANCE DATA'!$A$4:$AL$4,0),FALSE) -> #REF! | K19: =IF((G19+J19)=0,0,G19/(G19+J19)) -> #REF! | O19: ='ATTENDANCE DATA'!S4 -> 46190 | P19: =COUNTIF('ATTENDANCE DATA'!S7:S706,"P") -> 563 | Q19: =COUNTIF('ATTENDANCE DATA'!S7:S706,"A") -> 137
A20: =[1]!tblEmployee[[#This Row],[Emp_ID]] -> #REF! | B20: =VLOOKUP($A20,[1]!tblEmployee[#All],MATCH([1]Attendance_Data!B$2,[1]!tblEmployee[#Headers],0),FALSE) -> #REF! | C20: =VLOOKUP($A20,[1]!tblEmployee[#All],MATCH([1]Attendance_Data!C$2,[1]!tblEmployee[#Headers],0),FALSE) -> #REF! | D20: =VLOOKUP($A20,[1]!tblEmployee[#All],MATCH([1]Attendance_Data!D$2,[1]!tblEmployee[#Headers],0),FALSE) -> #REF! | E20: =VLOOKUP($A20,[1]!tblEmployee[#All],MATCH([1]Attendance_Data!E$2,[1]!tblEmployee[#Headers],0),FALSE) -> #REF! | F20: =VLOOKUP($A20,'ATTENDANCE DATA'!$A$4:$AL$706,MATCH([1]Attendance_Data!F$2,'ATTENDANCE DATA'!$A$4:$AL$4,0),FALSE) -> #REF! | G20: =VLOOKUP($A20,'ATTENDANCE DATA'!$A$4:$AL$706,MATCH([1]Attendance_Data!G$2,'ATTENDANCE DATA'!$A$4:$AL$4,0),FALSE) -> #REF! | H20: =VLOOKUP($A20,'ATTENDANCE DATA'!$A$4:$AL$706,MATCH([1]Attendance_Data!H$2,'ATTENDANCE DATA'!$A$4:$AL$4,0),FALSE) -> #REF! | I20: =VLOOKUP($A20,'ATTENDANCE DATA'!$A$4:$AL$706,MATCH([1]Attendance_Data!I$2,'ATTENDANCE DATA'!$A$4:$AL$4,0),FALSE) -> #REF! | J20: =VLOOKUP($A20,'ATTENDANCE DATA'!$A$4:$AL$706,MATCH([1]Attendance_Data!J$2,'ATTENDANCE DATA'!$A$4:$AL$4,0),FALSE) -> #REF! | K20: =IF((G20+J20)=0,0,G20/(G20+J20)) -> #REF! | O20: ='ATTENDANCE DATA'!T4 -> 46191 | P20: =COUNTIF('ATTENDANCE DATA'!T7:T706,"P") -> 0 | Q20: =COUNTIF('ATTENDANCE DATA'!T7:T706,"A") -> 0
A21: =[1]!tblEmployee[[#This Row],[Emp_ID]] -> #REF! | B21: =VLOOKUP($A21,[1]!tblEmployee[#All],MATCH([1]Attendance_Data!B$2,[1]!tblEmployee[#Headers],0),FALSE) -> #REF! | C21: =VLOOKUP($A21,[1]!tblEmployee[#All],MATCH([1]Attendance_Data!C$2,[1]!tblEmployee[#Headers],0),FALSE) -> #REF! | D21: =VLOOKUP($A21,[1]!tblEmployee[#All],MATCH([1]Attendance_Data!D$2,[1]!tblEmployee[#Headers],0),FALSE) -> #REF! | E21: =VLOOKUP($A21,[1]!tblEmployee[#All],MATCH([1]Attendance_Data!E$2,[1]!tblEmployee[#Headers],0),FALSE) -> #REF! | F21: =VLOOKUP($A21,'ATTENDANCE DATA'!$A$4:$AL$706,MATCH([1]Attendance_Data!F$2,'ATTENDANCE DATA'!$A$4:$AL$4,0),FALSE) -> #REF! | G21: =VLOOKUP($A21,'ATTENDANCE DATA'!$A$4:$AL$706,MATCH([1]Attendance_Data!G$2,'ATTENDANCE DATA'!$A$4:$AL$4,0),FALSE) -> #REF! | H21: =VLOOKUP($A21,'ATTENDANCE DATA'!$A$4:$AL$706,MATCH([1]Attendance_Data!H$2,'ATTENDANCE DATA'!$A$4:$AL$4,0),FALSE) -> #REF! | I21: =VLOOKUP($A21,'ATTENDANCE DATA'!$A$4:$AL$706,MATCH([1]Attendance_Data!I$2,'ATTENDANCE DATA'!$A$4:$AL$4,0),FALSE) -> #REF! | J21: =VLOOKUP($A21,'ATTENDANCE DATA'!$A$4:$AL$706,MATCH([1]Attendance_Data!J$2,'ATTENDANCE DATA'!$A$4:$AL$4,0),FALSE) -> #REF! | K21: =IF((G21+J21)=0,0,G21/(G21+J21)) -> #REF! | O21: ='ATTENDANCE DATA'!U4 -> 46192 | P21: =COUNTIF('ATTENDANCE DATA'!U7:U706,"P") -> 576 | Q21: =COUNTIF('ATTENDANCE DATA'!U7:U706,"A") -> 124
A22: =[1]!tblEmployee[[#This Row],[Emp_ID]] -> #REF! | B22: =VLOOKUP($A22,[1]!tblEmployee[#All],MATCH([1]Attendance_Data!B$2,[1]!tblEmployee[#Headers],0),FALSE) -> #REF! | C22: =VLOOKUP($A22,[1]!tblEmployee[#All],MATCH([1]Attendance_Data!C$2,[1]!tblEmployee[#Headers],0),FALSE) -> #REF! | D22: =VLOOKUP($A22,[1]!tblEmployee[#All],MATCH([1]Attendance_Data!D$2,[1]!tblEmployee[#Headers],0),FALSE) -> #REF! | E22: =VLOOKUP($A22,[1]!tblEmployee[#All],MATCH([1]Attendance_Data!E$2,[1]!tblEmployee[#Headers],0),FALSE) -> #REF! | F22: =VLOOKUP($A22,'ATTENDANCE DATA'!$A$4:$AL$706,MATCH([1]Attendance_Data!F$2,'ATTENDANCE DATA'!$A$4:$AL$4,0),FALSE) -> #REF! | G22: =VLOOKUP($A22,'ATTENDANCE DATA'!$A$4:$AL$706,MATCH([1]Attendance_Data!G$2,'ATTENDANCE DATA'!$A$4:$AL$4,0),FALSE) -> #REF! | H22: =VLOOKUP($A22,'ATTENDANCE DATA'!$A$4:$AL$706,MATCH([1]Attendance_Data!H$2,'ATTENDANCE DATA'!$A$4:$AL$4,0),FALSE) -> #REF! | I22: =VLOOKUP($A22,'ATTENDANCE DATA'!$A$4:$AL$706,MATCH([1]Attendance_Data!I$2,'ATTENDANCE DATA'!$A$4:$AL$4,0),FALSE) -> #REF! | J22: =VLOOKUP($A22,'ATTENDANCE DATA'!$A$4:$AL$706,MATCH([1]Attendance_Data!J$2,'ATTENDANCE DATA'!$A$4:$AL$4,0),FALSE) -> #REF! | K22: =IF((G22+J22)=0,0,G22/(G22+J22)) -> #REF! | O22: ='ATTENDANCE DATA'!V4 -> 46193 | P22: =COUNTIF('ATTENDANCE DATA'!V7:V706,"P") -> 580 | Q22: =COUNTIF('ATTENDANCE DATA'!V7:V706,"A") -> 120
A23: =[1]!tblEmployee[[#This Row],[Emp_ID]] -> #REF! | B23: =VLOOKUP($A23,[1]!tblEmployee[#All],MATCH([1]Attendance_Data!B$2,[1]!tblEmployee[#Headers],0),FALSE) -> #REF! | C23: =VLOOKUP($A23,[1]!tblEmployee[#All],MATCH([1]Attendance_Data!C$2,[1]!tblEmployee[#Headers],0),FALSE) -> #REF! | D23: =VLOOKUP($A23,[1]!tblEmployee[#All],MATCH([1]Attendance_Data!D$2,[1]!tblEmployee[#Headers],0),FALSE) -> #REF! | E23: =VLOOKUP($A23,[1]!tblEmployee[#All],MATCH([1]Attendance_Data!E$2,[1]!tblEmployee[#Headers],0),FALSE) -> #REF! | F23: =VLOOKUP($A23,'ATTENDANCE DATA'!$A$4:$AL$706,MATCH([1]Attendance_Data!F$2,'ATTENDANCE DATA'!$A$4:$AL$4,0),FALSE) -> #REF! | G23: =VLOOKUP($A23,'ATTENDANCE DATA'!$A$4:$AL$706,MATCH([1]Attendance_Data!G$2,'ATTENDANCE DATA'!$A$4:$AL$4,0),FALSE) -> #REF! | H23: =VLOOKUP($A23,'ATTENDANCE DATA'!$A$4:$AL$706,MATCH([1]Attendance_Data!H$2,'ATTENDANCE DATA'!$A$4:$AL$4,0),FALSE) -> #REF! | I23: =VLOOKUP($A23,'ATTENDANCE DATA'!$A$4:$AL$706,MATCH([1]Attendance_Data!I$2,'ATTENDANCE DATA'!$A$4:$AL$4,0),FALSE) -> #REF! | J23: =VLOOKUP($A23,'ATTENDANCE DATA'!$A$4:$AL$706,MATCH([1]Attendance_Data!J$2,'ATTENDANCE DATA'!$A$4:$AL$4,0),FALSE) -> #REF! | K23: =IF((G23+J23)=0,0,G23/(G23+J23)) -> #REF! | O23: ='ATTENDANCE DATA'!W4 -> 46194 | P23: =COUNTIF('ATTENDANCE DATA'!W7:W706,"P") -> 0 | Q23: =COUNTIF('ATTENDANCE DATA'!W7:W706,"A") -> 0
A24: =[1]!tblEmployee[[#This Row],[Emp_ID]] -> #REF! | B24: =VLOOKUP($A24,[1]!tblEmployee[#All],MATCH([1]Attendance_Data!B$2,[1]!tblEmployee[#Headers],0),FALSE) -> #REF! | C24: =VLOOKUP($A24,[1]!tblEmployee[#All],MATCH([1]Attendance_Data!C$2,[1]!tblEmployee[#Headers],0),FALSE) -> #REF! | D24: =VLOOKUP($A24,[1]!tblEmployee[#All],MATCH([1]Attendance_Data!D$2,[1]!tblEmployee[#Headers],0),FALSE) -> #REF! | E24: =VLOOKUP($A24,[1]!tblEmployee[#All],MATCH([1]Attendance_Data!E$2,[1]!tblEmployee[#Headers],0),FALSE) -> #REF! | F24: =VLOOKUP($A24,'ATTENDANCE DATA'!$A$4:$AL$706,MATCH([1]Attendance_Data!F$2,'ATTENDANCE DATA'!$A$4:$AL$4,0),FALSE) -> #REF! | G24: =VLOOKUP($A24,'ATTENDANCE DATA'!$A$4:$AL$706,MATCH([1]Attendance_Data!G$2,'ATTENDANCE DATA'!$A$4:$AL$4,0),FALSE) -> #REF! | H24: =VLOOKUP($A24,'ATTENDANCE DATA'!$A$4:$AL$706,MATCH([1]Attendance_Data!H$2,'ATTENDANCE DATA'!$A$4:$AL$4,0),FALSE) -> #REF! | I24: =VLOOKUP($A24,'ATTENDANCE DATA'!$A$4:$AL$706,MATCH([1]Attendance_Data!I$2,'ATTENDANCE DATA'!$A$4:$AL$4,0),FALSE) -> #REF! | J24: =VLOOKUP($A24,'ATTENDANCE DATA'!$A$4:$AL$706,MATCH([1]Attendance_Data!J$2,'ATTENDANCE DATA'!$A$4:$AL$4,0),FALSE) -> #REF! | K24: =IF((G24+J24)=0,0,G24/(G24+J24)) -> #REF! | O24: ='ATTENDANCE DATA'!X4 -> 46195 | P24: =COUNTIF('ATTENDANCE DATA'!X7:X706,"P") -> 579 | Q24: =COUNTIF('ATTENDANCE DATA'!X7:X706,"A") -> 121
A25: =[1]!tblEmployee[[#This Row],[Emp_ID]] -> #REF! | B25: =VLOOKUP($A25,[1]!tblEmployee[#All],MATCH([1]Attendance_Data!B$2,[1]!tblEmployee[#Headers],0),FALSE) -> #REF! | C25: =VLOOKUP($A25,[1]!tblEmployee[#All],MATCH([1]Attendance_Data!C$2,[1]!tblEmployee[#Headers],0),FALSE) -> #REF! | D25: =VLOOKUP($A25,[1]!tblEmployee[#All],MATCH([1]Attendance_Data!D$2,[1]!tblEmployee[#Headers],0),FALSE) -> #REF! | E25: =VLOOKUP($A25,[1]!tblEmployee[#All],MATCH([1]Attendance_Data!E$2,[1]!tblEmployee[#Headers],0),FALSE) -> #REF! | F25: =VLOOKUP($A25,'ATTENDANCE DATA'!$A$4:$AL$706,MATCH([1]Attendance_Data!F$2,'ATTENDANCE DATA'!$A$4:$AL$4,0),FALSE) -> #REF! | G25: =VLOOKUP($A25,'ATTENDANCE DATA'!$A$4:$AL$706,MATCH([1]Attendance_Data!G$2,'ATTENDANCE DATA'!$A$4:$AL$4,0),FALSE) -> #REF! | H25: =VLOOKUP($A25,'ATTENDANCE DATA'!$A$4:$AL$706,MATCH([1]Attendance_Data!H$2,'ATTENDANCE DATA'!$A$4:$AL$4,0),FALSE) -> #REF! | I25: =VLOOKUP($A25,'ATTENDANCE DATA'!$A$4:$AL$706,MATCH([1]Attendance_Data!I$2,'ATTENDANCE DATA'!$A$4:$AL$4,0),FALSE) -> #REF! | J25: =VLOOKUP($A25,'ATTENDANCE DATA'!$A$4:$AL$706,MATCH([1]Attendance_Data!J$2,'ATTENDANCE DATA'!$A$4:$AL$4,0),FALSE) -> #REF! | K25: =IF((G25+J25)=0,0,G25/(G25+J25)) -> #REF! | O25: ='ATTENDANCE DATA'!Y4 -> 46196 | P25: =COUNTIF('ATTENDANCE DATA'!Y7:Y706,"P") -> 574 | Q25: =COUNTIF('ATTENDANCE DATA'!Y7:Y706,"A") -> 126
A26: =[1]!tblEmployee[[#This Row],[Emp_ID]] -> #REF! | B26: =VLOOKUP($A26,[1]!tblEmployee[#All],MATCH([1]Attendance_Data!B$2,[1]!tblEmployee[#Headers],0),FALSE) -> #REF! | C26: =VLOOKUP($A26,[1]!tblEmployee[#All],MATCH([1]Attendance_Data!C$2,[1]!tblEmployee[#Headers],0),FALSE) -> #REF! | D26: =VLOOKUP($A26,[1]!tblEmployee[#All],MATCH([1]Attendance_Data!D$2,[1]!tblEmployee[#Headers],0),FALSE) -> #REF! | E26: =VLOOKUP($A26,[1]!tblEmployee[#All],MATCH([1]Attendance_Data!E$2,[1]!tblEmployee[#Headers],0),FALSE) -> #REF! | F26: =VLOOKUP($A26,'ATTENDANCE DATA'!$A$4:$AL$706,MATCH([1]Attendance_Data!F$2,'ATTENDANCE DATA'!$A$4:$AL$4,0),FALSE) -> #REF! | G26: =VLOOKUP($A26,'ATTENDANCE DATA'!$A$4:$AL$706,MATCH([1]Attendance_Data!G$2,'ATTENDANCE DATA'!$A$4:$AL$4,0),FALSE) -> #REF! | H26: =VLOOKUP($A26,'ATTENDANCE DATA'!$A$4:$AL$706,MATCH([1]Attendance_Data!H$2,'ATTENDANCE DATA'!$A$4:$AL$4,0),FALSE) -> #REF! | I26: =VLOOKUP($A26,'ATTENDANCE DATA'!$A$4:$AL$706,MATCH([1]Attendance_Data!I$2,'ATTENDANCE DATA'!$A$4:$AL$4,0),FALSE) -> #REF! | J26: =VLOOKUP($A26,'ATTENDANCE DATA'!$A$4:$AL$706,MATCH([1]Attendance_Data!J$2,'ATTENDANCE DATA'!$A$4:$AL$4,0),FALSE) -> #REF! | K26: =IF((G26+J26)=0,0,G26/(G26+J26)) -> #REF! | O26: ='ATTENDANCE DATA'!Z4 -> 46197 | P26: =COUNTIF('ATTENDANCE DATA'!Z7:Z706,"P") -> 569 | Q26: =COUNTIF('ATTENDANCE DATA'!Z7:Z706,"A") -> 131
A27: =[1]!tblEmployee[[#This Row],[Emp_ID]] -> #REF! | B27: =VLOOKUP($A27,[1]!tblEmployee[#All],MATCH([1]Attendance_Data!B$2,[1]!tblEmployee[#Headers],0),FALSE) -> #REF! | C27: =VLOOKUP($A27,[1]!tblEmployee[#All],MATCH([1]Attendance_Data!C$2,[1]!tblEmployee[#Headers],0),FALSE) -> #REF! | D27: =VLOOKUP($A27,[1]!tblEmployee[#All],MATCH([1]Attendance_Data!D$2,[1]!tblEmployee[#Headers],0),FALSE) -> #REF! | E27: =VLOOKUP($A27,[1]!tblEmployee[#All],MATCH([1]Attendance_Data!E$2,[1]!tblEmployee[#Headers],0),FALSE) -> #REF! | F27: =VLOOKUP($A27,'ATTENDANCE DATA'!$A$4:$AL$706,MATCH([1]Attendance_Data!F$2,'ATTENDANCE DATA'!$A$4:$AL$4,0),FALSE) -> #REF! | G27: =VLOOKUP($A27,'ATTENDANCE DATA'!$A$4:$AL$706,MATCH([1]Attendance_Data!G$2,'ATTENDANCE DATA'!$A$4:$AL$4,0),FALSE) -> #REF! | H27: =VLOOKUP($A27,'ATTENDANCE DATA'!$A$4:$AL$706,MATCH([1]Attendance_Data!H$2,'ATTENDANCE DATA'!$A$4:$AL$4,0),FALSE) -> #REF! | I27: =VLOOKUP($A27,'ATTENDANCE DATA'!$A$4:$AL$706,MATCH([1]Attendance_Data!I$2,'ATTENDANCE DATA'!$A$4:$AL$4,0),FALSE) -> #REF! | J27: =VLOOKUP($A27,'ATTENDANCE DATA'!$A$4:$AL$706,MATCH([1]Attendance_Data!J$2,'ATTENDANCE DATA'!$A$4:$AL$4,0),FALSE) -> #REF! | K27: =IF((G27+J27)=0,0,G27/(G27+J27)) -> #REF! | O27: ='ATTENDANCE DATA'!AA4 -> 46198 | P27: =COUNTIF('ATTENDANCE DATA'!AA7:AA706,"P") -> 571 | Q27: =COUNTIF('ATTENDANCE DATA'!AA7:AA706,"A") -> 129
A28: =[1]!tblEmployee[[#This Row],[Emp_ID]] -> #REF! | B28: =VLOOKUP($A28,[1]!tblEmployee[#All],MATCH([1]Attendance_Data!B$2,[1]!tblEmployee[#Headers],0),FALSE) -> #REF! | C28: =VLOOKUP($A28,[1]!tblEmployee[#All],MATCH([1]Attendance_Data!C$2,[1]!tblEmployee[#Headers],0),FALSE) -> #REF! | D28: =VLOOKUP($A28,[1]!tblEmployee[#All],MATCH([1]Attendance_Data!D$2,[1]!tblEmployee[#Headers],0),FALSE) -> #REF! | E28: =VLOOKUP($A28,[1]!tblEmployee[#All],MATCH([1]Attendance_Data!E$2,[1]!tblEmployee[#Headers],0),FALSE) -> #REF! | F28: =VLOOKUP($A28,'ATTENDANCE DATA'!$A$4:$AL$706,MATCH([1]Attendance_Data!F$2,'ATTENDANCE DATA'!$A$4:$AL$4,0),FALSE) -> #REF! | G28: =VLOOKUP($A28,'ATTENDANCE DATA'!$A$4:$AL$706,MATCH([1]Attendance_Data!G$2,'ATTENDANCE DATA'!$A$4:$AL$4,0),FALSE) -> #REF! | H28: =VLOOKUP($A28,'ATTENDANCE DATA'!$A$4:$AL$706,MATCH([1]Attendance_Data!H$2,'ATTENDANCE DATA'!$A$4:$AL$4,0),FALSE) -> #REF! | I28: =VLOOKUP($A28,'ATTENDANCE DATA'!$A$4:$AL$706,MATCH([1]Attendance_Data!I$2,'ATTENDANCE DATA'!$A$4:$AL$4,0),FALSE) -> #REF! | J28: =VLOOKUP($A28,'ATTENDANCE DATA'!$A$4:$AL$706,MATCH([1]Attendance_Data!J$2,'ATTENDANCE DATA'!$A$4:$AL$4,0),FALSE) -> #REF! | K28: =IF((G28+J28)=0,0,G28/(G28+J28)) -> #REF! | O28: ='ATTENDANCE DATA'!AB4 -> 46199 | P28: =COUNTIF('ATTENDANCE DATA'!AB7:AB706,"P") -> 0 | Q28: =COUNTIF('ATTENDANCE DATA'!AB7:AB706,"A") -> 0
A29: =[1]!tblEmployee[[#This Row],[Emp_ID]] -> #REF! | B29: =VLOOKUP($A29,[1]!tblEmployee[#All],MATCH([1]Attendance_Data!B$2,[1]!tblEmployee[#Headers],0),FALSE) -> #REF! | C29: =VLOOKUP($A29,[1]!tblEmployee[#All],MATCH([1]Attendance_Data!C$2,[1]!tblEmployee[#Headers],0),FALSE) -> #REF! | D29: =VLOOKUP($A29,[1]!tblEmployee[#All],MATCH([1]Attendance_Data!D$2,[1]!tblEmployee[#Headers],0),FALSE) -> #REF! | E29: =VLOOKUP($A29,[1]!tblEmployee[#All],MATCH([1]Attendance_Data!E$2,[1]!tblEmployee[#Headers],0),FALSE) -> #REF! | F29: =VLOOKUP($A29,'ATTENDANCE DATA'!$A$4:$AL$706,MATCH([1]Attendance_Data!F$2,'ATTENDANCE DATA'!$A$4:$AL$4,0),FALSE) -> #REF! | G29: =VLOOKUP($A29,'ATTENDANCE DATA'!$A$4:$AL$706,MATCH([1]Attendance_Data!G$2,'ATTENDANCE DATA'!$A$4:$AL$4,0),FALSE) -> #REF! | H29: =VLOOKUP($A29,'ATTENDANCE DATA'!$A$4:$AL$706,MATCH([1]Attendance_Data!H$2,'ATTENDANCE DATA'!$A$4:$AL$4,0),FALSE) -> #REF! | I29: =VLOOKUP($A29,'ATTENDANCE DATA'!$A$4:$AL$706,MATCH([1]Attendance_Data!I$2,'ATTENDANCE DATA'!$A$4:$AL$4,0),FALSE) -> #REF! | J29: =VLOOKUP($A29,'ATTENDANCE DATA'!$A$4:$AL$706,MATCH([1]Attendance_Data!J$2,'ATTENDANCE DATA'!$A$4:$AL$4,0),FALSE) -> #REF! | K29: =IF((G29+J29)=0,0,G29/(G29+J29)) -> #REF! | O29: ='ATTENDANCE DATA'!AC4 -> 46200 | P29: =COUNTIF('ATTENDANCE DATA'!AC7:AC706,"P") -> 585 | Q29: =COUNTIF('ATTENDANCE DATA'!AC7:AC706,"A") -> 115
A30: =[1]!tblEmployee[[#This Row],[Emp_ID]] -> #REF! | B30: =VLOOKUP($A30,[1]!tblEmployee[#All],MATCH([1]Attendance_Data!B$2,[1]!tblEmployee[#Headers],0),FALSE) -> #REF! | C30: =VLOOKUP($A30,[1]!tblEmployee[#All],MATCH([1]Attendance_Data!C$2,[1]!tblEmployee[#Headers],0),FALSE) -> #REF! | D30: =VLOOKUP($A30,[1]!tblEmployee[#All],MATCH([1]Attendance_Data!D$2,[1]!tblEmployee[#Headers],0),FALSE) -> #REF! | E30: =VLOOKUP($A30,[1]!tblEmployee[#All],MATCH([1]Attendance_Data!E$2,[1]!tblEmployee[#Headers],0),FALSE) -> #REF! | F30: =VLOOKUP($A30,'ATTENDANCE DATA'!$A$4:$AL$706,MATCH([1]Attendance_Data!F$2,'ATTENDANCE DATA'!$A$4:$AL$4,0),FALSE) -> #REF! | G30: =VLOOKUP($A30,'ATTENDANCE DATA'!$A$4:$AL$706,MATCH([1]Attendance_Data!G$2,'ATTENDANCE DATA'!$A$4:$AL$4,0),FALSE) -> #REF! | H30: =VLOOKUP($A30,'ATTENDANCE DATA'!$A$4:$AL$706,MATCH([1]Attendance_Data!H$2,'ATTENDANCE DATA'!$A$4:$AL$4,0),FALSE) -> #REF! | I30: =VLOOKUP($A30,'ATTENDANCE DATA'!$A$4:$AL$706,MATCH([1]Attendance_Data!I$2,'ATTENDANCE DATA'!$A$4:$AL$4,0),FALSE) -> #REF! | J30: =VLOOKUP($A30,'ATTENDANCE DATA'!$A$4:$AL$706,MATCH([1]Attendance_Data!J$2,'ATTENDANCE DATA'!$A$4:$AL$4,0),FALSE) -> #REF! | K30: =IF((G30+J30)=0,0,G30/(G30+J30)) -> #REF! | O30: ='ATTENDANCE DATA'!AD4 -> 46201 | P30: =COUNTIF('ATTENDANCE DATA'!AD7:AD706,"P") -> 0 | Q30: =COUNTIF('ATTENDANCE DATA'!AD7:AD706,"A") -> 0
A31: =[1]!tblEmployee[[#This Row],[Emp_ID]] -> #REF! | B31: =VLOOKUP($A31,[1]!tblEmployee[#All],MATCH([1]Attendance_Data!B$2,[1]!tblEmployee[#Headers],0),FALSE) -> #REF! | C31: =VLOOKUP($A31,[1]!tblEmployee[#All],MATCH([1]Attendance_Data!C$2,[1]!tblEmployee[#Headers],0),FALSE) -> #REF! | D31: =VLOOKUP($A31,[1]!tblEmployee[#All],MATCH([1]Attendance_Data!D$2,[1]!tblEmployee[#Headers],0),FALSE) -> #REF! | E31: =VLOOKUP($A31,[1]!tblEmployee[#All],MATCH([1]Attendance_Data!E$2,[1]!tblEmployee[#Headers],0),FALSE) -> #REF! | F31: =VLOOKUP($A31,'ATTENDANCE DATA'!$A$4:$AL$706,MATCH([1]Attendance_Data!F$2,'ATTENDANCE DATA'!$A$4:$AL$4,0),FALSE) -> #REF! | G31: =VLOOKUP($A31,'ATTENDANCE DATA'!$A$4:$AL$706,MATCH([1]Attendance_Data!G$2,'ATTENDANCE DATA'!$A$4:$AL$4,0),FALSE) -> #REF! | H31: =VLOOKUP($A31,'ATTENDANCE DATA'!$A$4:$AL$706,MATCH([1]Attendance_Data!H$2,'ATTENDANCE DATA'!$A$4:$AL$4,0),FALSE) -> #REF! | I31: =VLOOKUP($A31,'ATTENDANCE DATA'!$A$4:$AL$706,MATCH([1]Attendance_Data!I$2,'ATTENDANCE DATA'!$A$4:$AL$4,0),FALSE) -> #REF! | J31: =VLOOKUP($A31,'ATTENDANCE DATA'!$A$4:$AL$706,MATCH([1]Attendance_Data!J$2,'ATTENDANCE DATA'!$A$4:$AL$4,0),FALSE) -> #REF! | K31: =IF((G31+J31)=0,0,G31/(G31+J31)) -> #REF! | O31: ='ATTENDANCE DATA'!AE4 -> 46202 | P31: =COUNTIF('ATTENDANCE DATA'!AE7:AE706,"P") -> 563 | Q31: =COUNTIF('ATTENDANCE DATA'!AE7:AE706,"A") -> 137
A32: =[1]!tblEmployee[[#This Row],[Emp_ID]] -> #REF! | B32: =VLOOKUP($A32,[1]!tblEmployee[#All],MATCH([1]Attendance_Data!B$2,[1]!tblEmployee[#Headers],0),FALSE) -> #REF! | C32: =VLOOKUP($A32,[1]!tblEmployee[#All],MATCH([1]Attendance_Data!C$2,[1]!tblEmployee[#Headers],0),FALSE) -> #REF! | D32: =VLOOKUP($A32,[1]!tblEmployee[#All],MATCH([1]Attendance_Data!D$2,[1]!tblEmployee[#Headers],0),FALSE) -> #REF! | E32: =VLOOKUP($A32,[1]!tblEmployee[#All],MATCH([1]Attendance_Data!E$2,[1]!tblEmployee[#Headers],0),FALSE) -> #REF! | F32: =VLOOKUP($A32,'ATTENDANCE DATA'!$A$4:$AL$706,MATCH([1]Attendance_Data!F$2,'ATTENDANCE DATA'!$A$4:$AL$4,0),FALSE) -> #REF! | G32: =VLOOKUP($A32,'ATTENDANCE DATA'!$A$4:$AL$706,MATCH([1]Attendance_Data!G$2,'ATTENDANCE DATA'!$A$4:$AL$4,0),FALSE) -> #REF! | H32: =VLOOKUP($A32,'ATTENDANCE DATA'!$A$4:$AL$706,MATCH([1]Attendance_Data!H$2,'ATTENDANCE DATA'!$A$4:$AL$4,0),FALSE) -> #REF! | I32: =VLOOKUP($A32,'ATTENDANCE DATA'!$A$4:$AL$706,MATCH([1]Attendance_Data!I$2,'ATTENDANCE DATA'!$A$4:$AL$4,0),FALSE) -> #REF! | J32: =VLOOKUP($A32,'ATTENDANCE DATA'!$A$4:$AL$706,MATCH([1]Attendance_Data!J$2,'ATTENDANCE DATA'!$A$4:$AL$4,0),FALSE) -> #REF! | K32: =IF((G32+J32)=0,0,G32/(G32+J32)) -> #REF! | O32: ='ATTENDANCE DATA'!AF4 -> 46203 | P32: =COUNTIF('ATTENDANCE DATA'!AF7:AF706,"P") -> 578 | Q32: =COUNTIF('ATTENDANCE DATA'!AF7:AF706,"A") -> 122
A33: =[1]!tblEmployee[[#This Row],[Emp_ID]] -> #REF! | B33: =VLOOKUP($A33,[1]!tblEmployee[#All],MATCH([1]Attendance_Data!B$2,[1]!tblEmployee[#Headers],0),FALSE) -> #REF! | C33: =VLOOKUP($A33,[1]!tblEmployee[#All],MATCH([1]Attendance_Data!C$2,[1]!tblEmployee[#Headers],0),FALSE) -> #REF! | D33: =VLOOKUP($A33,[1]!tblEmployee[#All],MATCH([1]Attendance_Data!D$2,[1]!tblEmployee[#Headers],0),FALSE) -> #REF! | E33: =VLOOKUP($A33,[1]!tblEmployee[#All],MATCH([1]Attendance_Data!E$2,[1]!tblEmployee[#Headers],0),FALSE) -> #REF! | F33: =VLOOKUP($A33,'ATTENDANCE DATA'!$A$4:$AL$706,MATCH([1]Attendance_Data!F$2,'ATTENDANCE DATA'!$A$4:$AL$4,0),FALSE) -> #REF! | G33: =VLOOKUP($A33,'ATTENDANCE DATA'!$A$4:$AL$706,MATCH([1]Attendance_Data!G$2,'ATTENDANCE DATA'!$A$4:$AL$4,0),FALSE) -> #REF! | H33: =VLOOKUP($A33,'ATTENDANCE DATA'!$A$4:$AL$706,MATCH([1]Attendance_Data!H$2,'ATTENDANCE DATA'!$A$4:$AL$4,0),FALSE) -> #REF! | I33: =VLOOKUP($A33,'ATTENDANCE DATA'!$A$4:$AL$706,MATCH([1]Attendance_Data!I$2,'ATTENDANCE DATA'!$A$4:$AL$4,0),FALSE) -> #REF! | J33: =VLOOKUP($A33,'ATTENDANCE DATA'!$A$4:$AL$706,MATCH([1]Attendance_Data!J$2,'ATTENDANCE DATA'!$A$4:$AL$4,0),FALSE) -> #REF! | K33: =IF((G33+J33)=0,0,G33/(G33+J33)) -> #REF!
A34: =[1]!tblEmployee[[#This Row],[Emp_ID]] -> #REF! | B34: =VLOOKUP($A34,[1]!tblEmployee[#All],MATCH([1]Attendance_Data!B$2,[1]!tblEmployee[#Headers],0),FALSE) -> #REF! | C34: =VLOOKUP($A34,[1]!tblEmployee[#All],MATCH([1]Attendance_Data!C$2,[1]!tblEmployee[#Headers],0),FALSE) -> #REF! | D34: =VLOOKUP($A34,[1]!tblEmployee[#All],MATCH([1]Attendance_Data!D$2,[1]!tblEmployee[#Headers],0),FALSE) -> #REF! | E34: =VLOOKUP($A34,[1]!tblEmployee[#All],MATCH([1]Attendance_Data!E$2,[1]!tblEmployee[#Headers],0),FALSE) -> #REF! | F34: =VLOOKUP($A34,'ATTENDANCE DATA'!$A$4:$AL$706,MATCH([1]Attendance_Data!F$2,'ATTENDANCE DATA'!$A$4:$AL$4,0),FALSE) -> #REF! | G34: =VLOOKUP($A34,'ATTENDANCE DATA'!$A$4:$AL$706,MATCH([1]Attendance_Data!G$2,'ATTENDANCE DATA'!$A$4:$AL$4,0),FALSE) -> #REF! | H34: =VLOOKUP($A34,'ATTENDANCE DATA'!$A$4:$AL$706,MATCH([1]Attendance_Data!H$2,'ATTENDANCE DATA'!$A$4:$AL$4,0),FALSE) -> #REF! | I34: =VLOOKUP($A34,'ATTENDANCE DATA'!$A$4:$AL$706,MATCH([1]Attendance_Data!I$2,'ATTENDANCE DATA'!$A$4:$AL$4,0),FALSE) -> #REF! | J34: =VLOOKUP($A34,'ATTENDANCE DATA'!$A$4:$AL$706,MATCH([1]Attendance_Data!J$2,'ATTENDANCE DATA'!$A$4:$AL$4,0),FALSE) -> #REF! | K34: =IF((G34+J34)=0,0,G34/(G34+J34)) -> #REF!
A35: =[1]!tblEmployee[[#This Row],[Emp_ID]] -> #REF! | B35: =VLOOKUP($A35,[1]!tblEmployee[#All],MATCH([1]Attendance_Data!B$2,[1]!tblEmployee[#Headers],0),FALSE) -> #REF! | C35: =VLOOKUP($A35,[1]!tblEmployee[#All],MATCH([1]Attendance_Data!C$2,[1]!tblEmployee[#Headers],0),FALSE) -> #REF! | D35: =VLOOKUP($A35,[1]!tblEmployee[#All],MATCH([1]Attendance_Data!D$2,[1]!tblEmployee[#Headers],0),FALSE) -> #REF! | E35: =VLOOKUP($A35,[1]!tblEmployee[#All],MATCH([1]Attendance_Data!E$2,[1]!tblEmployee[#Headers],0),FALSE) -> #REF! | F35: =VLOOKUP($A35,'ATTENDANCE DATA'!$A$4:$AL$706,MATCH([1]Attendance_Data!F$2,'ATTENDANCE DATA'!$A$4:$AL$4,0),FALSE) -> #REF! | G35: =VLOOKUP($A35,'ATTENDANCE DATA'!$A$4:$AL$706,MATCH([1]Attendance_Data!G$2,'ATTENDANCE DATA'!$A$4:$AL$4,0),FALSE) -> #REF! | H35: =VLOOKUP($A35,'ATTENDANCE DATA'!$A$4:$AL$706,MATCH([1]Attendance_Data!H$2,'ATTENDANCE DATA'!$A$4:$AL$4,0),FALSE) -> #REF! | I35: =VLOOKUP($A35,'ATTENDANCE DATA'!$A$4:$AL$706,MATCH([1]Attendance_Data!I$2,'ATTENDANCE DATA'!$A$4:$AL$4,0),FALSE) -> #REF! | J35: =VLOOKUP($A35,'ATTENDANCE DATA'!$A$4:$AL$706,MATCH([1]Attendance_Data!J$2,'ATTENDANCE DATA'!$A$4:$AL$4,0),FALSE) -> #REF! | K35: =IF((G35+J35)=0,0,G35/(G35+J35)) -> #REF!
A36: =[1]!tblEmployee[[#This Row],[Emp_ID]] -> #REF! | B36: =VLOOKUP($A36,[1]!tblEmployee[#All],MATCH([1]Attendance_Data!B$2,[1]!tblEmployee[#Headers],0),FALSE) -> #REF! | C36: =VLOOKUP($A36,[1]!tblEmployee[#All],MATCH([1]Attendance_Data!C$2,[1]!tblEmployee[#Headers],0),FALSE) -> #REF! | D36: =VLOOKUP($A36,[1]!tblEmployee[#All],MATCH([1]Attendance_Data!D$2,[1]!tblEmployee[#Headers],0),FALSE) -> #REF! | E36: =VLOOKUP($A36,[1]!tblEmployee[#All],MATCH([1]Attendance_Data!E$2,[1]!tblEmployee[#Headers],0),FALSE) -> #REF! | F36: =VLOOKUP($A36,'ATTENDANCE DATA'!$A$4:$AL$706,MATCH([1]Attendance_Data!F$2,'ATTENDANCE DATA'!$A$4:$AL$4,0),FALSE) -> #REF! | G36: =VLOOKUP($A36,'ATTENDANCE DATA'!$A$4:$AL$706,MATCH([1]Attendance_Data!G$2,'ATTENDANCE DATA'!$A$4:$AL$4,0),FALSE) -> #REF! | H36: =VLOOKUP($A36,'ATTENDANCE DATA'!$A$4:$AL$706,MATCH([1]Attendance_Data!H$2,'ATTENDANCE DATA'!$A$4:$AL$4,0),FALSE) -> #REF! | I36: =VLOOKUP($A36,'ATTENDANCE DATA'!$A$4:$AL$706,MATCH([1]Attendance_Data!I$2,'ATTENDANCE DATA'!$A$4:$AL$4,0),FALSE) -> #REF! | J36: =VLOOKUP($A36,'ATTENDANCE DATA'!$A$4:$AL$706,MATCH([1]Attendance_Data!J$2,'ATTENDANCE DATA'!$A$4:$AL$4,0),FALSE) -> #REF! | K36: =IF((G36+J36)=0,0,G36/(G36+J36)) -> #REF!
A37: =[1]!tblEmployee[[#This Row],[Emp_ID]] -> #REF! | B37: =VLOOKUP($A37,[1]!tblEmployee[#All],MATCH([1]Attendance_Data!B$2,[1]!tblEmployee[#Headers],0),FALSE) -> #REF! | C37: =VLOOKUP($A37,[1]!tblEmployee[#All],MATCH([1]Attendance_Data!C$2,[1]!tblEmployee[#Headers],0),FALSE) -> #REF! | D37: =VLOOKUP($A37,[1]!tblEmployee[#All],MATCH([1]Attendance_Data!D$2,[1]!tblEmployee[#Headers],0),FALSE) -> #REF! | E37: =VLOOKUP($A37,[1]!tblEmployee[#All],MATCH([1]Attendance_Data!E$2,[1]!tblEmployee[#Headers],0),FALSE) -> #REF! | F37: =VLOOKUP($A37,'ATTENDANCE DATA'!$A$4:$AL$706,MATCH([1]Attendance_Data!F$2,'ATTENDANCE DATA'!$A$4:$AL$4,0),FALSE) -> #REF! | G37: =VLOOKUP($A37,'ATTENDANCE DATA'!$A$4:$AL$706,MATCH([1]Attendance_Data!G$2,'ATTENDANCE DATA'!$A$4:$AL$4,0),FALSE) -> #REF! | H37: =VLOOKUP($A37,'ATTENDANCE DATA'!$A$4:$AL$706,MATCH([1]Attendance_Data!H$2,'ATTENDANCE DATA'!$A$4:$AL$4,0),FALSE) -> #REF! | I37: =VLOOKUP($A37,'ATTENDANCE DATA'!$A$4:$AL$706,MATCH([1]Attendance_Data!I$2,'ATTENDANCE DATA'!$A$4:$AL$4,0),FALSE) -> #REF! | J37: =VLOOKUP($A37,'ATTENDANCE DATA'!$A$4:$AL$706,MATCH([1]Attendance_Data!J$2,'ATTENDANCE DATA'!$A$4:$AL$4,0),FALSE) -> #REF! | K37: =IF((G37+J37)=0,0,G37/(G37+J37)) -> #REF!
A38: =[1]!tblEmployee[[#This Row],[Emp_ID]] -> #REF! | B38: =VLOOKUP($A38,[1]!tblEmployee[#All],MATCH([1]Attendance_Data!B$2,[1]!tblEmployee[#Headers],0),FALSE) -> #REF! | C38: =VLOOKUP($A38,[1]!tblEmployee[#All],MATCH([1]Attendance_Data!C$2,[1]!tblEmployee[#Headers],0),FALSE) -> #REF! | D38: =VLOOKUP($A38,[1]!tblEmployee[#All],MATCH([1]Attendance_Data!D$2,[1]!tblEmployee[#Headers],0),FALSE) -> #REF! | E38: =VLOOKUP($A38,[1]!tblEmployee[#All],MATCH([1]Attendance_Data!E$2,[1]!tblEmployee[#Headers],0),FALSE) -> #REF! | F38: =VLOOKUP($A38,'ATTENDANCE DATA'!$A$4:$AL$706,MATCH([1]Attendance_Data!F$2,'ATTENDANCE DATA'!$A$4:$AL$4,0),FALSE) -> #REF! | G38: =VLOOKUP($A38,'ATTENDANCE DATA'!$A$4:$AL$706,MATCH([1]Attendance_Data!G$2,'ATTENDANCE DATA'!$A$4:$AL$4,0),FALSE) -> #REF! | H38: =VLOOKUP($A38,'ATTENDANCE DATA'!$A$4:$AL$706,MATCH([1]Attendance_Data!H$2,'ATTENDANCE DATA'!$A$4:$AL$4,0),FALSE) -> #REF! | I38: =VLOOKUP($A38,'ATTENDANCE DATA'!$A$4:$AL$706,MATCH([1]Attendance_Data!I$2,'ATTENDANCE DATA'!$A$4:$AL$4,0),FALSE) -> #REF! | J38: =VLOOKUP($A38,'ATTENDANCE DATA'!$A$4:$AL$706,MATCH([1]Attendance_Data!J$2,'ATTENDANCE DATA'!$A$4:$AL$4,0),FALSE) -> #REF! | K38: =IF((G38+J38)=0,0,G38/(G38+J38)) -> #REF!
A39: =[1]!tblEmployee[[#This Row],[Emp_ID]] -> #REF! | B39: =VLOOKUP($A39,[1]!tblEmployee[#All],MATCH([1]Attendance_Data!B$2,[1]!tblEmployee[#Headers],0),FALSE) -> #REF! | C39: =VLOOKUP($A39,[1]!tblEmployee[#All],MATCH([1]Attendance_Data!C$2,[1]!tblEmployee[#Headers],0),FALSE) -> #REF! | D39: =VLOOKUP($A39,[1]!tblEmployee[#All],MATCH([1]Attendance_Data!D$2,[1]!tblEmployee[#Headers],0),FALSE) -> #REF! | E39: =VLOOKUP($A39,[1]!tblEmployee[#All],MATCH([1]Attendance_Data!E$2,[1]!tblEmployee[#Headers],0),FALSE) -> #REF! | F39: =VLOOKUP($A39,'ATTENDANCE DATA'!$A$4:$AL$706,MATCH([1]Attendance_Data!F$2,'ATTENDANCE DATA'!$A$4:$AL$4,0),FALSE) -> #REF! | G39: =VLOOKUP($A39,'ATTENDANCE DATA'!$A$4:$AL$706,MATCH([1]Attendance_Data!G$2,'ATTENDANCE DATA'!$A$4:$AL$4,0),FALSE) -> #REF! | H39: =VLOOKUP($A39,'ATTENDANCE DATA'!$A$4:$AL$706,MATCH([1]Attendance_Data!H$2,'ATTENDANCE DATA'!$A$4:$AL$4,0),FALSE) -> #REF! | I39: =VLOOKUP($A39,'ATTENDANCE DATA'!$A$4:$AL$706,MATCH([1]Attendance_Data!I$2,'ATTENDANCE DATA'!$A$4:$AL$4,0),FALSE) -> #REF! | J39: =VLOOKUP($A39,'ATTENDANCE DATA'!$A$4:$AL$706,MATCH([1]Attendance_Data!J$2,'ATTENDANCE DATA'!$A$4:$AL$4,0),FALSE) -> #REF! | K39: =IF((G39+J39)=0,0,G39/(G39+J39)) -> #REF!
A40: =[1]!tblEmployee[[#This Row],[Emp_ID]] -> #REF! | B40: =VLOOKUP($A40,[1]!tblEmployee[#All],MATCH([1]Attendance_Data!B$2,[1]!tblEmployee[#Headers],0),FALSE) -> #REF! | C40: =VLOOKUP($A40,[1]!tblEmployee[#All],MATCH([1]Attendance_Data!C$2,[1]!tblEmployee[#Headers],0),FALSE) -> #REF! | D40: =VLOOKUP($A40,[1]!tblEmployee[#All],MATCH([1]Attendance_Data!D$2,[1]!tblEmployee[#Headers],0),FALSE) -> #REF! | E40: =VLOOKUP($A40,[1]!tblEmployee[#All],MATCH([1]Attendance_Data!E$2,[1]!tblEmployee[#Headers],0),FALSE) -> #REF! | F40: =VLOOKUP($A40,'ATTENDANCE DATA'!$A$4:$AL$706,MATCH([1]Attendance_Data!F$2,'ATTENDANCE DATA'!$A$4:$AL$4,0),FALSE) -> #REF! | G40: =VLOOKUP($A40,'ATTENDANCE DATA'!$A$4:$AL$706,MATCH([1]Attendance_Data!G$2,'ATTENDANCE DATA'!$A$4:$AL$4,0),FALSE) -> #REF! | H40: =VLOOKUP($A40,'ATTENDANCE DATA'!$A$4:$AL$706,MATCH([1]Attendance_Data!H$2,'ATTENDANCE DATA'!$A$4:$AL$4,0),FALSE) -> #REF! | I40: =VLOOKUP($A40,'ATTENDANCE DATA'!$A$4:$AL$706,MATCH([1]Attendance_Data!I$2,'ATTENDANCE DATA'!$A$4:$AL$4,0),FALSE) -> #REF! | J40: =VLOOKUP($A40,'ATTENDANCE DATA'!$A$4:$AL$706,MATCH([1]Attendance_Data!J$2,'ATTENDANCE DATA'!$A$4:$AL$4,0),FALSE) -> #REF! | K40: =IF((G40+J40)=0,0,G40/(G40+J40)) -> #REF!
A41: =[1]!tblEmployee[[#This Row],[Emp_ID]] -> #REF! | B41: =VLOOKUP($A41,[1]!tblEmployee[#All],MATCH([1]Attendance_Data!B$2,[1]!tblEmployee[#Headers],0),FALSE) -> #REF! | C41: =VLOOKUP($A41,[1]!tblEmployee[#All],MATCH([1]Attendance_Data!C$2,[1]!tblEmployee[#Headers],0),FALSE) -> #REF! | D41: =VLOOKUP($A41,[1]!tblEmployee[#All],MATCH([1]Attendance_Data!D$2,[1]!tblEmployee[#Headers],0),FALSE) -> #REF! | E41: =VLOOKUP($A41,[1]!tblEmployee[#All],MATCH([1]Attendance_Data!E$2,[1]!tblEmployee[#Headers],0),FALSE) -> #REF! | F41: =VLOOKUP($A41,'ATTENDANCE DATA'!$A$4:$AL$706,MATCH([1]Attendance_Data!F$2,'ATTENDANCE DATA'!$A$4:$AL$4,0),FALSE) -> #REF! | G41: =VLOOKUP($A41,'ATTENDANCE DATA'!$A$4:$AL$706,MATCH([1]Attendance_Data!G$2,'ATTENDANCE DATA'!$A$4:$AL$4,0),FALSE) -> #REF! | H41: =VLOOKUP($A41,'ATTENDANCE DATA'!$A$4:$AL$706,MATCH([1]Attendance_Data!H$2,'ATTENDANCE DATA'!$A$4:$AL$4,0),FALSE) -> #REF! | I41: =VLOOKUP($A41,'ATTENDANCE DATA'!$A$4:$AL$706,MATCH([1]Attendance_Data!I$2,'ATTENDANCE DATA'!$A$4:$AL$4,0),FALSE) -> #REF! | J41: =VLOOKUP($A41,'ATTENDANCE DATA'!$A$4:$AL$706,MATCH([1]Attendance_Data!J$2,'ATTENDANCE DATA'!$A$4:$AL$4,0),FALSE) -> #REF! | K41: =IF((G41+J41)=0,0,G41/(G41+J41)) -> #REF!
A42: =[1]!tblEmployee[[#This Row],[Emp_ID]] -> #REF! | B42: =VLOOKUP($A42,[1]!tblEmployee[#All],MATCH([1]Attendance_Data!B$2,[1]!tblEmployee[#Headers],0),FALSE) -> #REF! | C42: =VLOOKUP($A42,[1]!tblEmployee[#All],MATCH([1]Attendance_Data!C$2,[1]!tblEmployee[#Headers],0),FALSE) -> #REF! | D42: =VLOOKUP($A42,[1]!tblEmployee[#All],MATCH([1]Attendance_Data!D$2,[1]!tblEmployee[#Headers],0),FALSE) -> #REF! | E42: =VLOOKUP($A42,[1]!tblEmployee[#All],MATCH([1]Attendance_Data!E$2,[1]!tblEmployee[#Headers],0),FALSE) -> #REF! | F42: =VLOOKUP($A42,'ATTENDANCE DATA'!$A$4:$AL$706,MATCH([1]Attendance_Data!F$2,'ATTENDANCE DATA'!$A$4:$AL$4,0),FALSE) -> #REF! | G42: =VLOOKUP($A42,'ATTENDANCE DATA'!$A$4:$AL$706,MATCH([1]Attendance_Data!G$2,'ATTENDANCE DATA'!$A$4:$AL$4,0),FALSE) -> #REF! | H42: =VLOOKUP($A42,'ATTENDANCE DATA'!$A$4:$AL$706,MATCH([1]Attendance_Data!H$2,'ATTENDANCE DATA'!$A$4:$AL$4,0),FALSE) -> #REF! | I42: =VLOOKUP($A42,'ATTENDANCE DATA'!$A$4:$AL$706,MATCH([1]Attendance_Data!I$2,'ATTENDANCE DATA'!$A$4:$AL$4,0),FALSE) -> #REF! | J42: =VLOOKUP($A42,'ATTENDANCE DATA'!$A$4:$AL$706,MATCH([1]Attendance_Data!J$2,'ATTENDANCE DATA'!$A$4:$AL$4,0),FALSE) -> #REF! | K42: =IF((G42+J42)=0,0,G42/(G42+J42)) -> #REF!
A43: =[1]!tblEmployee[[#This Row],[Emp_ID]] -> #REF! | B43: =VLOOKUP($A43,[1]!tblEmployee[#All],MATCH([1]Attendance_Data!B$2,[1]!tblEmployee[#Headers],0),FALSE) -> #REF! | C43: =VLOOKUP($A43,[1]!tblEmployee[#All],MATCH([1]Attendance_Data!C$2,[1]!tblEmployee[#Headers],0),FALSE) -> #REF! | D43: =VLOOKUP($A43,[1]!tblEmployee[#All],MATCH([1]Attendance_Data!D$2,[1]!tblEmployee[#Headers],0),FALSE) -> #REF! | E43: =VLOOKUP($A43,[1]!tblEmployee[#All],MATCH([1]Attendance_Data!E$2,[1]!tblEmployee[#Headers],0),FALSE) -> #REF! | F43: =VLOOKUP($A43,'ATTENDANCE DATA'!$A$4:$AL$706,MATCH([1]Attendance_Data!F$2,'ATTENDANCE DATA'!$A$4:$AL$4,0),FALSE) -> #REF! | G43: =VLOOKUP($A43,'ATTENDANCE DATA'!$A$4:$AL$706,MATCH([1]Attendance_Data!G$2,'ATTENDANCE DATA'!$A$4:$AL$4,0),FALSE) -> #REF! | H43: =VLOOKUP($A43,'ATTENDANCE DATA'!$A$4:$AL$706,MATCH([1]Attendance_Data!H$2,'ATTENDANCE DATA'!$A$4:$AL$4,0),FALSE) -> #REF! | I43: =VLOOKUP($A43,'ATTENDANCE DATA'!$A$4:$AL$706,MATCH([1]Attendance_Data!I$2,'ATTENDANCE DATA'!$A$4:$AL$4,0),FALSE) -> #REF! | J43: =VLOOKUP($A43,'ATTENDANCE DATA'!$A$4:$AL$706,MATCH([1]Attendance_Data!J$2,'ATTENDANCE DATA'!$A$4:$AL$4,0),FALSE) -> #REF! | K43: =IF((G43+J43)=0,0,G43/(G43+J43)) -> #REF!
A44: =[1]!tblEmployee[[#This Row],[Emp_ID]] -> #REF! | B44: =VLOOKUP($A44,[1]!tblEmployee[#All],MATCH([1]Attendance_Data!B$2,[1]!tblEmployee[#Headers],0),FALSE) -> #REF! | C44: =VLOOKUP($A44,[1]!tblEmployee[#All],MATCH([1]Attendance_Data!C$2,[1]!tblEmployee[#Headers],0),FALSE) -> #REF! | D44: =VLOOKUP($A44,[1]!tblEmployee[#All],MATCH([1]Attendance_Data!D$2,[1]!tblEmployee[#Headers],0),FALSE) -> #REF! | E44: =VLOOKUP($A44,[1]!tblEmployee[#All],MATCH([1]Attendance_Data!E$2,[1]!tblEmployee[#Headers],0),FALSE) -> #REF! | F44: =VLOOKUP($A44,'ATTENDANCE DATA'!$A$4:$AL$706,MATCH([1]Attendance_Data!F$2,'ATTENDANCE DATA'!$A$4:$AL$4,0),FALSE) -> #REF! | G44: =VLOOKUP($A44,'ATTENDANCE DATA'!$A$4:$AL$706,MATCH([1]Attendance_Data!G$2,'ATTENDANCE DATA'!$A$4:$AL$4,0),FALSE) -> #REF! | H44: =VLOOKUP($A44,'ATTENDANCE DATA'!$A$4:$AL$706,MATCH([1]Attendance_Data!H$2,'ATTENDANCE DATA'!$A$4:$AL$4,0),FALSE) -> #REF! | I44: =VLOOKUP($A44,'ATTENDANCE DATA'!$A$4:$AL$706,MATCH([1]Attendance_Data!I$2,'ATTENDANCE DATA'!$A$4:$AL$4,0),FALSE) -> #REF! | J44: =VLOOKUP($A44,'ATTENDANCE DATA'!$A$4:$AL$706,MATCH([1]Attendance_Data!J$2,'ATTENDANCE DATA'!$A$4:$AL$4,0),FALSE) -> #REF! | K44: =IF((G44+J44)=0,0,G44/(G44+J44)) -> #REF!
... A702: =[1]!tblEmployee[[#This Row],[Emp_ID]] -> #REF! | B702: =VLOOKUP($A702,[1]!tblEmployee[#All],MATCH([1]Attendance_Data!B$2,[1]!tblEmployee[#Headers],0),FALSE) -> #REF! | C702: =VLOOKUP($A702,[1]!tblEmployee[#All],MATCH([1]Attendance_Data!C$2,[1]!tblEmployee[#Headers],0),FALSE) -> #REF! | D702: =VLOOKUP($A702,[1]!tblEmployee[#All],MATCH([1]Attendance_Data!D$2,[1]!tblEmployee[#Headers],0),FALSE) -> #REF! | E702: =VLOOKUP($A702,[1]!tblEmployee[#All],MATCH([1]Attendance_Data!E$2,[1]!tblEmployee[#Headers],0),FALSE) -> #REF! | F702: =VLOOKUP($A702,'ATTENDANCE DATA'!$A$4:$AL$706,MATCH([1]Attendance_Data!F$2,'ATTENDANCE DATA'!$A$4:$AL$4,0),FALSE) -> #REF! | G702: =VLOOKUP($A702,'ATTENDANCE DATA'!$A$4:$AL$706,MATCH([1]Attendance_Data!G$2,'ATTENDANCE DATA'!$A$4:$AL$4,0),FALSE) -> #REF! | H702: =VLOOKUP($A702,'ATTENDANCE DATA'!$A$4:$AL$706,MATCH([1]Attendance_Data!H$2,'ATTENDANCE DATA'!$A$4:$AL$4,0),FALSE) -> #REF! | I702: =VLOOKUP($A702,'ATTENDANCE DATA'!$A$4:$AL$706,MATCH([1]Attendance_Data!I$2,'ATTENDANCE DATA'!$A$4:$AL$4,0),FALSE) -> #REF! | J702: =VLOOKUP($A702,'ATTENDANCE DATA'!$A$4:$AL$706,MATCH([1]Attendance_Data!J$2,'ATTENDANCE DATA'!$A$4:$AL$4,0),FALSE) -> #REF! | K702: =IF((G702+J702)=0,0,G702/(G702+J702)) -> #REF!

Sheet ATTENDANCE DATA
A1: Month | B1: Year | C1: ="Fully Automatic Attendance Sheet - "&A2&" "&B2 -> Fully Automatic Attendance Sheet - June 2026 | AH1: DataMentix
A2: June | B2: 2026
A3: =DATEVALUE("1"&A2&B2) -> 46174 | B3: =EOMONTH(A3,0) -> 46203
A4: Emp_ID | B4: Emp_Name | C4: =A3 -> 46174 | D4: =IF(C4<$B$3,C4+1,"") -> 46175 | E4: =IF(D4<$B$3,D4+1,"") -> 46176 | F4: =IF(E4<$B$3,E4+1,"") -> 46177 | G4: =IF(F4<$B$3,F4+1,"") -> 46178 | H4: =IF(G4<$B$3,G4+1,"") -> 46179 | I4: =IF(H4<$B$3,H4+1,"") -> 46180 | J4: =IF(I4<$B$3,I4+1,"") -> 46181 | K4: =IF(J4<$B$3,J4+1,"") -> 46182 | ... AG4: =IF(AF4<$B$3,AF4+1,"") | AH4: Total Days | AI4: Present | AJ4: Holiday | AK4: Week Off | AL4: Absent
C5: =TEXT(C4,"ddd") -> Mon | D5: =TEXT(D4,"ddd") -> Tue | E5: =TEXT(E4,"ddd") -> Wed | F5: =TEXT(F4,"ddd") -> Thu | G5: =TEXT(G4,"ddd") -> Fri | H5: =TEXT(H4,"ddd") -> Sat | I5: =TEXT(I4,"ddd") -> Sun | J5: =TEXT(J4,"ddd") -> Mon | ... AG5: =TEXT(AG4,"ddd")
A7: =[1]Employee_Master!A3 -> EMP001 | B7: =[1]Employee_Master!B3 -> Aman Khan | C7: P | D7: P | E7: P | F7: P | G7: A | H7: P | J7: P | K7: P | L7: H | M7: P | N7: P | O7: P | Q7: P | R7: A | S7: P | T7: H | U7: P | V7: P | X7: A | Y7: P | Z7: P | AA7: P | AB7: H | AC7: P | AE7: P | AF7: P | AH7: =COUNT(C$4:AG$4) -> 30 | AI7: =COUNTIF($C7:$AG7,"P") -> 20 | AJ7: =COUNTIF($C7:$AG7,"H") -> 3 | AK7: =COUNTIF(C$5:AG$6,"Sun") -> 4 | AL7: =COUNTIF($C7:$AG7,"A") -> 3
A8: =[1]Employee_Master!A4 -> EMP002 | B8: =[1]Employee_Master!B4 -> Neha Sharma | C8: P | D8: A | E8: P | F8: P | G8: P | H8: P | J8: P | K8: P | L8: H | M8: P | N8: P | O8: A | Q8: P | R8: A | S8: P | T8: H | U8: P | V8: P | X8: A | Y8: A | Z8: P | AA8: P | AB8: H | AC8: P | AE8: P | AF8: P | AH8: =COUNT(C$4:AG$4) -> 30 | AI8: =COUNTIF($C8:$AG8,"P") -> 18 | AJ8: =COUNTIF($C8:$AG8,"H") -> 3 | AK8: =COUNTIF(C$5:AG$6,"Sun") -> 4 | AL8: =COUNTIF($C8:$AG8,"A") -> 5
A9: =[1]Employee_Master!A5 -> EMP003 | B9: =[1]Employee_Master!B5 -> Ali Raza | C9: P | D9: P | E9: P | F9: P | G9: P | H9: P | J9: P | K9: A | L9: H | M9: A | N9: P | O9: A | Q9: P | R9: P | S9: P | T9: H | U9: P | V9: P | X9: P | Y9: A | Z9: P | AA9: P | AB9: H | AC9: P | AE9: P | AF9: P | AH9: =COUNT(C$4:AG$4) -> 30 | AI9: =COUNTIF($C9:$AG9,"P") -> 19 | AJ9: =COUNTIF($C9:$AG9,"H") -> 3 | AK9: =COUNTIF(C$5:AG$6,"Sun") -> 4 | AL9: =COUNTIF($C9:$AG9,"A") -> 4
A10: =[1]Employee_Master!A6 -> EMP004 | B10: =[1]Employee_Master!B6 -> Riya Singh | C10: P | D10: P | E10: P | F10: P | G10: A | H10: P | J10: P | K10: A | L10: H | M10: A | N10: A | O10: A | Q10: P | R10: P | S10: P | T10: H | U10: P | V10: A | X10: P | Y10: A | Z10: A | AA10: P | AB10: H | AC10: P | AE10: P | AF10: P | AH10: =COUNT(C$4:AG$4) -> 30 | AI10: =COUNTIF($C10:$AG10,"P") -> 15 | AJ10: =COUNTIF($C10:$AG10,"H") -> 3 | AK10: =COUNTIF(C$5:AG$6,"Sun") -> 4 | AL10: =COUNTIF($C10:$AG10,"A") -> 8
A11: =[1]Employee_Master!A7 -> EMP005 | B11: =[1]Employee_Master!B7 -> Shah Alam | C11: P | D11: P | E11: P | F11: P | G11: P | H11: P | J11: P | K11: P | L11: H | M11: P | N11: P | O11: A | Q11: P | R11: A | S11: P | T11: H | U11: P | V11: P | X11: P | Y11: P | Z11: P | AA11: P | AB11: H | AC11: P | AE11: A | AF11: P | AH11: =COUNT(C$4:AG$4) -> 30 | AI11: =COUNTIF($C11:$AG11,"P") -> 20 | AJ11: =COUNTIF($C11:$AG11,"H") -> 3 | AK11: =COUNTIF(C$5:AG$6,"Sun") -> 4 | AL11: =COUNTIF($C11:$AG11,"A") -> 3
A12: =[1]Employee_Master!A8 -> EMP006 | B12: =[1]Employee_Master!B8 -> Karan Gupta | C12: P | D12: P | E12: P | F12: P | G12: P | H12: P | J12: P | K12: P | L12: H | M12: P | N12: P | O12: P | Q12: P | R12: P | S12: P | T12: H | U12: P | V12: A | X12: A | Y12: P | Z12: P | AA12: P | AB12: H | AC12: P | AE12: A | AF12: P | AH12: =COUNT(C$4:AG$4) -> 30 | AI12: =COUNTIF($C12:$AG12,"P") -> 20 | AJ12: =COUNTIF($C12:$AG12,"H") -> 3 | AK12: =COUNTIF(C$5:AG$6,"Sun") -> 4 | AL12: =COUNTIF($C12:$AG12,"A") -> 3
A13: =[1]Employee_Master!A9 -> EMP007 | B13: =[1]Employee_Master!B9 -> Irfan Pathan | C13: P | D13: P | E13: P | F13: P | G13: A | H13: P | J13: A | K13: P | L13: H | M13: A | N13: P | O13: P | Q13: P | R13: A | S13: P | T13: H | U13: P | V13: P | X13: A | Y13: P | Z13: P | AA13: P | AB13: H | AC13: P | AE13: P | AF13: P | AH13: =COUNT(C$4:AG$4) -> 30 | AI13: =COUNTIF($C13:$AG13,"P") -> 18 | AJ13: =COUNTIF($C13:$AG13,"H") -> 3 | AK13: =COUNTIF(C$5:AG$6,"Sun") -> 4 | AL13: =COUNTIF($C13:$AG13,"A") -> 5
A14: =[1]Employee_Master!A10 -> EMP008 | B14: =[1]Employee_Master!B10 -> Pappi Singh | C14: A | D14: P | E14: P | F14: P | G14: A | H14: P | J14: A | K14: P | L14: H | M14: A | N14: A | O14: P | Q14: P | R14: P | S14: P | T14: H | U14: P | V14: P | X14: P | Y14: A | Z14: P | AA14: P | AB14: H | AC14: P | AE14: P | AF14: P | AH14: =COUNT(C$4:AG$4) -> 30 | AI14: =COUNTIF($C14:$AG14,"P") -> 17 | AJ14: =COUNTIF($C14:$AG14,"H") -> 3 | AK14: =COUNTIF(C$5:AG$6,"Sun") -> 4 | AL14: =COUNTIF($C14:$AG14,"A") -> 6
A15: =[1]Employee_Master!A11 -> EMP009 | B15: =[1]Employee_Master!B11 -> Raju Roi | C15: P | D15: P | E15: P | F15: P | G15: A | H15: P | J15: P | K15: P | L15: H | M15: P | N15: A | O15: P | Q15: P | R15: A | S15: P | T15: H | U15: A | V15: P | X15: P | Y15: P | Z15: P | AA15: P | AB15: H | AC15: P | AE15: P | AF15: P | AH15: =COUNT(C$4:AG$4) -> 30 | AI15: =COUNTIF($C15:$AG15,"P") -> 19 | AJ15: =COUNTIF($C15:$AG15,"H") -> 3 | AK15: =COUNTIF(C$5:AG$6,"Sun") -> 4 | AL15: =COUNTIF($C15:$AG15,"A") -> 4
A16: =[1]Employee_Master!A12 -> EMP010 | B16: =[1]Employee_Master!B12 -> Rabia Ansari | C16: A | D16: P | E16: A | F16: P | G16: P | H16: P | J16: P | K16: P | L16: H | M16: P | N16: P | O16: P | Q16: P | R16: P | S16: P | T16: H | U16: P | V16: P | X16: P | Y16: A | Z16: P | AA16: P | AB16: H | AC16: P | AE16: P | AF16: P | AH16: =COUNT(C$4:AG$4) -> 30 | AI16: =COUNTIF($C16:$AG16,"P") -> 20 | AJ16: =COUNTIF($C16:$AG16,"H") -> 3 | AK16: =COUNTIF(C$5:AG$6,"Sun") -> 4 | AL16: =COUNTIF($C16:$AG16,"A") -> 3
A17: =[1]Employee_Master!A13 -> EMP011 | B17: =[1]Employee_Master!B13 -> Ram Kumar | C17: P | D17: P | E17: P | F17: A | G17: P | H17: P | J17: P | K17: A | L17: H | M17: A | N17: P | O17: P | Q17: P | R17: P | S17: P | T17: H | U17: P | V17: P | X17: P | Y17: P | Z17: P | AA17: P | AB17: H | AC17: P | AE17: A | AF17: P | AH17: =COUNT(C$4:AG$4) -> 30 | AI17: =COUNTIF($C17:$AG17,"P") -> 19 | AJ17: =COUNTIF($C17:$AG17,"H") -> 3 | AK17: =COUNTIF(C$5:AG$6,"Sun") -> 4 | AL17: =COUNTIF($C17:$AG17,"A") -> 4
A18: =[1]Employee_Master!A14 -> EMP012 | B18: =[1]Employee_Master!B14 -> Raja Babu | C18: P | D18: P | E18: P | F18: P | G18: P | H18: P | J18: A | K18: P | L18: H | M18: P | N18: P | O18: P | Q18: P | R18: P | S18: P | T18: H | U18: A | V18: P | X18: P | Y18: P | Z18: P | AA18: P | AB18: H | AC18: P | AE18: P | AF18: A | AH18: =COUNT(C$4:AG$4) -> 30 | AI18: =COUNTIF($C18:$AG18,"P") -> 20 | AJ18: =COUNTIF($C18:$AG18,"H") -> 3 | AK18: =COUNTIF(C$5:AG$6,"Sun") -> 4 | AL18: =COUNTIF($C18:$AG18,"A") -> 3
... A706: =[1]Employee_Master!A702 -> EMP0700 | B706: =[1]Employee_Master!B702 -> Asif Jain | C706: P | D706: P | E706: A | F706: A | G706: P | H706: P | J706: P | K706: P | L706: H | M706: P | N706: P | O706: P | Q706: A | R706: P | S706: P | T706: H | U706: P | V706: P | X706: P | Y706: P | Z706: P | AA706: P | AB706: H | AC706: P | AE706: P | AF706: P | AH706: =COUNT(C$4:AG$4) -> 30 | AI706: =COUNTIF($C706:$AG706,"P") -> 20 | AJ706: =COUNTIF($C706:$AG706,"H") -> 3 | AK706: =COUNTIF(C$5:AG$6,"Sun") -> 4 | AL706: =COUNTIF($C706:$AG706,"A") -> 3

Sheet Payroll_main
A1: Year | B1: Month | C1: Payroll | D1: Annual Payroll Plan | E1: Standard Hours | F1: Actual Hours
A2: 2025 | B2: JAN | C2: 107635 | D2: 120000 | E2: 0.33 | F2: 0.71
A3: 2025 | B3: FEB | C3: 153595 | D3: 120000 | E3: 0.17 | F3: 0.5
A4: 2025 | B4: MAR | C4: 156760 | D4: 120000 | E4: 0.64 | F4: 0.64
A5: 2025 | B5: APR | C5: 160805 | D5: 120000 | E5: 0.4 | F5: 0.24
A6: 2025 | B6: MAY | C6: 220180 | D6: 120000 | E6: 0.2 | F6: 0.25
A7: 2025 | B7: JUN | C7: 254540 | D7: 120000 | E7: 0.44 | F7: 0.69
A8: 2025 | B8: JUL | C8: 254180 | D8: 120000 | E8: 0.24 | F8: 0.41
A9: 2025 | B9: AUG | C9: 253290 | D9: 120000 | E9: 0.75 | F9: 0.6
A10: 2025 | B10: SEP | C10: 242850 | D10: 120000 | E10: 0.73 | F10: 0.5
A11: 2025 | B11: OCT | C11: 237680 | D11: 120000 | E11: 0.72 | F11: 0.47
A12: 2025 | B12: NOV | C12: 197370 | D12: 120000 | E12: 0.73 | F12: 0.75
A13: 2025 | B13: DEC | C13: 98395 | D13: 120000 | E13: 0.36 | F13: 0.28
... A49: 2028 | B49: DEC | C49: 331775 | D49: 250000 | E49: 0.22 | F49: 0.45

Sheet Payroll_Department
A2: Year | B2: Month | C2: Department | D2: Payroll
A3: 2025 | B3: JAN | C3: Management | D3: 28340
A4: 2025 | B4: FEB | C4: Management | D4: 33090
A5: 2025 | B5: MAR | C5: Management | D5: 31685
A6: 2025 | B6: APR | C6: Management | D6: 36840
A7: 2025 | B7: MAY | C7: Management | D7: 64590
A8: 2025 | B8: JUN | C8: Management | D8: 76530
A9: 2025 | B9: JUL | C9: Management | D9: 84020
A10: 2025 | B10: AUG | C10: Management | D10: 84170
A11: 2025 | B11: SEP | C11: Management | D11: 78630
A12: 2025 | B12: OCT | C12: Management | D12: 60760
A13: 2025 | B13: NOV | C13: Management | D13: 44165
A14: 2025 | B14: DEC | C14: Management | D14: 21930
... A242: 2028 | B242: DEC | C242: Logistics Department | D242: 66650

Sheet Payroll_Cost
A1: Year | B1: Month | C1: Cost Type | D1: Percentage
A2: 2025 | B2: JAN | C2: Basic Payroll | D2: 0.4
A3: 2025 | B3: FEB | C3: Basic Payroll | D3: 0.37
A4: 2025 | B4: MAR | C4: Basic Payroll | D4: 0.35
A5: 2025 | B5: APR | C5: Basic Payroll | D5: 0.36
A6: 2025 | B6: MAY | C6: Basic Payroll | D6: 0.36
A7: 2025 | B7: JUN | C7: Basic Payroll | D7: 0.38
A8: 2025 | B8: JUL | C8: Basic Payroll | D8: 0.37
A9: 2025 | B9: AUG | C9: Basic Payroll | D9: 0.37
A10: 2025 | B10: SEP | C10: Basic Payroll | D10: 0.37
A11: 2025 | B11: OCT | C11: Basic Payroll | D11: 0.39
A12: 2025 | B12: NOV | C12: Basic Payroll | D12: 0.38
A13: 2025 | B13: DEC | C13: Basic Payroll | D13: 0.4
... A145: 2028 | B145: DEC | C145: Payroll Taxes & Insurance | D145: 0.16

Sheet Payroll_Forecast
A1: Year | B1: Month | C1: Day | D1: Planned Payroll | E1: Actual Payroll
A2: 2025 | B2: APR | C2: FR | D2: 8141 | E2: 40200
A3: 2025 | B3: APR | C3: MO | D3: 32559 | E3: 42659
A4: 2025 | B4: APR | C4: SA | D4: 34285 | E4: 33754
A5: 2025 | B5: APR | C5: SU | D5: 28363 | E5: 19542
A6: 2025 | B6: APR | C6: TH | D6: 89111 | E6: 40007
A7: 2025 | B7: APR | C7: TU | D7: 2859 | E7: 40003
A8: 2025 | B8: APR | C8: WE | D8: 44682 | E8: 20115
A9: 2025 | B9: AUG | C9: FR | D9: 26085 | E9: 13391
A10: 2025 | B10: AUG | C10: MO | D10: 48774 | E10: 49917
A11: 2025 | B11: AUG | C11: SA | D11: 34286 | E11: 35803
A12: 2025 | B12: AUG | C12: SU | D12: 44592 | E12: 56058
A13: 2025 | B13: AUG | C13: TH | D13: 32862 | E13: 4345
... A337: 2028 | B337: SEP | C337: WE | D337: 90957 | E337: 20641

Sheet PAYROLL ANALYSIS PIVOT TABLE
A1: PAYROLL ANALYSIS PIVOT TABLE & CHARTS
A6: 1 | B6: MONTHY PAYROLL
B7: Year | C7: (All)
B9: Row Labels | C9: Sum of Payroll
B10: JAN | C10: 1113010
B11: FEB | C11: 1166195
B12: MAR | C12: 1034385
B13: APR | C13: 935630
B14: MAY | C14: 1376655
B15: JUN | C15: 1283040
B16: JUL | C16: 1289080
B17: AUG | C17: 1112665
B18: SEP | C18: 1504150
B19: OCT | C19: 1258380
B20: NOV | C20: 1262370
B21: DEC | C21: 907720
B22: Grand Total | C22: 14243280
A29: 2
A30: 2 | B30: DEPARTMENT WISE- PAYROLL
B31: Year | C31: (All)
B32: Month | C32: (All)
B34: Row Labels | C34: Sum of Payroll
B35: Administrative Staff | C35: 2830140
B36: Logistics Department | C36: 2196820
B37: Management | C37: 3781025
B38: Production Department | C38: 2587050
B39: Sales Department | C39: 2848245
B40: Grand Total | C40: 14243280
A49: 3 | B49: PLANNED VS ACTUAL PAYROLL
B50: Year | C50: (All)
B52: Row Labels | C52: Sum of Annual Payroll Plan | D52: Sum of Payroll | E52: PAYROLL VARIANCE
B53: JAN | C53: 697500 | D53: 1113010 | E53: =D65-C65 -> 5873280
B54: FEB | C54: 697500 | D54: 1166195
B55: MAR | C55: 697500 | D55: 1034385
B56: APR | C56: 697500 | D56: 935630
B57: MAY | C57: 697500 | D57: 1376655
B58: JUN | C58: 697500 | D58: 1283040
B59: JUL | C59: 697500 | D59: 1289080
B60: AUG | C60: 697500 | D60: 1112665
B61: SEP | C61: 697500 | D61: 1504150
B62: OCT | C62: 697500 | D62: 1258380
B63: NOV | C63: 697500 | D63: 1262370
B64: DEC | C64: 697500 | D64: 907720
B65: Grand Total | C65: 8370000 | D65: 14243280
A71: 4 | B71: PAYROLL COST BREAKDOWN
B72: Row Labels | C72: Average of Percentage
B73: Basic Payroll | C73: 0.374375
B74: Bonuses and Prizes | C74: 0.47375
B75: Payroll Taxes & Insurance | C75: 0.151875
B76: Grand Total | C76: 0.33333333
A91: 5 | B91: STANDARD VS ACTUAL HOURS
B92: Year | C92: (All)
B94: Row Labels | C94: Sum of Actual Hours | D94: Sum of Standard Hours
B95: JAN | C95: 2.51 | D95: 2.02
B96: FEB | C96: 2.39 | D96: 1.47
B97: MAR | C97: 2.6 | D97: 1.71
B98: APR | C98: 1.88 | D98: 2
B99: MAY | C99: 1.74 | D99: 1.28
B100: JUN | C100: 1.98 | D100: 1.92
B101: JUL | C101: 1.64 | D101: 1.28
B102: AUG | C102: 2.26 | D102: 2.02
B103: SEP | C103: 2.57 | D103: 2.16
B104: OCT | C104: 1.45 | D104: 2.17
B105: NOV | C105: 2.03 | D105: 2.21
B106: DEC | C106: 2.08 | D106: 1.52
B107: Grand Total | C107: 25.13 | D107: 21.76

Sheet ATTENDANCE ANALYSIS PIVOT TABLE
A1: ATTENDANCE ANALYSIS PIVOT TABLE & CHARTS
A5: 1 | B5: DAILY ATTENDANCE
B6: Row Labels | C6: Sum of Present | D6: Sum of Absent
B7: 46174 | C7: 572 | D7: 128
B8: 46176 | C8: 576 | D8: 124
B9: 46178 | C9: 588 | D9: 112
B10: 46181 | C10: 572 | D10: 128
B11: 46192 | C11: 576 | D11: 124
B12: 46193 | C12: 580 | D12: 120
B13: 46195 | C13: 579 | D13: 121
B14: 46196 | C14: 574 | D14: 126
B15: 46200 | C15: 585 | D15: 115
B16: 46203 | C16: 578 | D16: 122
B17: Grand Total | C17: 5780 | D17: 1220
A26: 2 | B26: DEPARTMENT ATTENDANCE
B27: Row Labels | C27: Sum of Present | D27: Sum of Absent
B28: Engineering | C28: 1517 | D28: 346
B29: HR | C29: 1395 | D29: 330
B30: Management | C30: 1374 | D30: 328
B31: Procurement | C31: 1527 | D31: 359
B32: Technical | C32: 1341 | D32: 292
B33: Grand Total | C33: 7154 | D33: 1655
A46: 3 | B46: ATTENDANCE STATUS
B47: Status | C47: Total
B48: Present | C48: =SUM(GETPIVOTDATA("Sum of Present",$B$27)) -> 7154
B49: Absent | C49: =SUM(GETPIVOTDATA("Sum of Absent",$B$27)) -> 1655
B50: Holiday | C50: =SUM(Table97[Holiday]) -> #REF!
B51: Week Off | C51: =SUM(Table97[[#All],[Week Off]]) -> #REF!
A67: 4 | B67: ATTENDANCE BY GENDER
B68: Row Labels | C68: Sum of Present | D68: Sum of Absent | E68: AVG
B69: Female | C69: 5927 | D69: 1364 | E69: =GETPIVOTDATA("Sum of Present",$B$68,"Gender","Female")/(GETPIVOTDATA("Sum of Present",$B$68,"Gender","Female")+GETPIVOTDATA("Sum of Absent",$B$68,"Gender","Female")) -> 0.81292004
B70: Male | C70: 7192 | D70: 1617 | E70: =GETPIVOTDATA("Sum of Present",$B$68,"Gender","Male")/(GETPIVOTDATA("Sum of Present",$B$68,"Gender","Male")+GETPIVOTDATA("Sum of Absent",$B$68,"Gender","Male")) -> 0.81643773
B71: Grand Total | C71: 13119 | D71: 2981 | E71: =GETPIVOTDATA("Sum of Present",$B$68)/(GETPIVOTDATA("Sum of Present",$B$68)+GETPIVOTDATA("Sum of Absent",$B$68)) -> 0.81484472

Sheet HR OVERVIEW PIVOT TABLE
A1: HR OVERVIEW PIVOT TABLE & CHARTS
A5: 1 | B5: EMPLOYEE COUNT BY DEPARTMENT
B6: Row Labels | C6: Count of Emp_ID
B7: Admin | C7: 71
B8: Engineering | C8: 81
B9: Finance | C9: 61
B10: HR | C10: 75
B11: IT | C11: 61
B12: Management | C12: 74
B13: Procurement | C13: 82
B14: Sales | C14: 63
B15: Support | C15: 61
B16: Technical | C16: 71
B17: Grand Total | C17: 700
A26: 2 | B26: EMPLOYEE COUNT BY DESIGNATION
B27: Row Labels | C27: Count of Emp_ID
B28: Technician | C28: 30
B29: Helper | C29: 32
B30: Sr. Technician | C30: 33
B31: Manager | C31: 34
B32: Sr. Engineer | C32: 35
B33: Assistant Manager | C33: 40
B34: Engineer | C34: 46
B35: Coordinator | C35: 100
B36: Officer | C36: 143
B37: Executive | C37: 199
B38: Grand Total | C38: 692
A46: 3 | B46: GENDER DISTRIBUTION
B47: Row Labels | C47: Count of Emp_ID
B48: Female | C48: 317
B49: Male | C49: 383
B50: Grand Total | C50: 700
A67: 4 | B67: AVERAGE SALARY BY DEPARTMENT
B68: Row Labels | C68: Average of Basic Salary
B69: Admin | C69: 56103.634
B70: Engineering | C70: 56936.617
B71: Finance | C71: 56706.082
B72: HR | C72: 55739.707
B73: IT | C73: 56207.492
B74: Management | C74: 57245.459
B75: Procurement | C75: 56826.646
B76: Sales | C76: 57085.238
B77: Support | C77: 54210.18
B78: Technical | C78: 52839.746
B79: Grand Total | C79: 56020.274

Sheet HR DASHBOARD
A1: Employee Attendance & Payroll MIS
A2: HR Overview Dashboard

Sheet ATTENDANCE DASHBOARD
B1: Employee Attendance & Payroll MIS
B3: Attendance Analysis Dashboard

Sheet PAYROLL DASHBOARD
A2: Employee Attendance & Payroll MIS
A3: Payroll Analysis Dashboard

Sheet INSIGHTS DASHBOARD
A1: Employee Attendance & Payroll MIS
A3: Key Insights & Recommendations
